hardware/include/defines.v
`define ALU_ADD 4'b0000
`define ALU_SUB 4`b1000
`define ALU_SLL 4'b0001
`define ALU_SLT 4'b0010
`define ALU_SLTU 4'b0011
`define ALU_XOR 4'b1000
`define ALU_SRL 4'b0101
`define ALU_SRA 4'b1101
`define ALU_OR   4'b0110
`define ALU_AND  4'b0111

hardware/src/alu.v
`include "defines.v"

module alu (
    input wire [31:0] a,
    input wire [31:0] b,
    input wire [3:0] alu_op,
    output reg [31:0] result,
    output wire zero
);

    assign zero = (result == 32'b0);

    always @(*) begin
        case (alu_op)
            `ALU_ADD: result = a + b;
            `ALU_SUB: result = a - b;
            `ALU_AND: result = a & b;
            `ALU_OR: result = a | b;
            `ALU_XOR: result = a ^ b;
            `ALU_SLL: result = a << b[4:0];
            `ALU_SRL: result = a >> b[4:0];
            `ALU_SRA: result = $signed(a) >>> b [4:0] ;
            `ALU_SLT: result = ($signed(a) < $signed(b)) ? 32'b1 : 32'b0;
            `ALU_SLTU: result = (a < b) ? 32'b1 : 32'b0;
            default: result = 32'b0;
        endcase
    end
    
endmodule

hardware/src/regfile.v
module regfile (
    input wire clk,
    input wire we,
    input wire [4:0] rs1_addr,
    input wire [4:0] rs2_addr,
    input wire [4:0] rd_addr,
    input wire [31:0] rd_data,
    output wire [31:0] rs1_data,
    output wire [31:0] rs2_data
);
    reg [31:0] regs [31:0];

    assign rs1_data = (rs1_addr == 5'b0) ? 32'b0 : regs[rs1_addr];
    assign rs2_data = (rs2_addr == 5'b0) ? 32'b0 : regs[rs2_addr];

    integer i;
    initial begin
        for (i = 0; i < 32; i = i + 1) regs[i] = 32'b0;
    end

    always @(posedge clk) begin
        if (we && (rd_addr != 5'b0)) begin
            regs[rd_addr] <= rd_data;
        end
    end

endmodule

hardware/src/memory.v
module memory (
    input wire clk,
    input wire we,
    /* verilator lint_off UNUSEDSIGNAL */
    input wire [31:0] addr,
    /* verilator lint_off UNUSEDSIGNAL */
    input wire [31:0] write_data,
    output wire [31:0] read_data
);
    reg [31:0] ram [1023:0];

    assign read_data = ram[addr[11:2]];

    always @(posedge clk) begin
        if (we) begin
            ram[addr[11:2]] <= write_data;
        end

    end

    integer i;
    initial begin
        for (i = 0; i < 1024; i = i + 1) begin
            ram[i] = 32'b0;
        end
    end
    
endmodule

hardware/src/top.v
module top (
    input wire clk,
    input wire rst_n,
    output wire [31:0] debug_pc,
    output wire [31:0] debug_instr,
    output wire [31:0] debug_alu_out
);
    reg [31:0] pc;
    always @(posedge clk or negedge rst_n) begin
        if (!rst_n) begin
            pc <= 32'b0;
        end
        else begin
            pc <= pc + 4;
        end
    end

    /* verilator lint_off UNUSEDSIGNAL */
    wire [31:0] instr;
    /* verilator lint_on UNUSEDSIGNAL */

    memory inst_mem (
        .clk(clk),
        .we(1'b0),
        .addr(pc),
        .write_data(32'b0),
        .read_data(instr)
    );

    wire [6:0] opcode = instr[6:0];
    wire [4:0] rd = instr[11:7];
    wire [4:0] rs1 = instr[19:15];
    wire [4:0] rs2 = instr[24:20];

    wire [31:0] rs1_data, rs2_data;

    wire [31:0] imm_i = {{20{instr[31]}}, instr[31:20]};
    wire [31:0] imm_s = {{20{instr[31]}}, instr[31:25], instr[11:7]};
    wire [31:0] imm = (opcode == 7'b0100011) ? imm_s : imm_i;

    wire is_lw = (opcode == 7'b0000011);
    wire is_sw = (opcode == 7'b0100011);
    wire reg_we = (opcode == 7'b0010011 || opcode == 7'b0110011 || is_lw);

    wire [31:0] mem_read_data;

    memory data_mem (
        .clk(clk),
        .we(is_sw),
        .addr(alu_out),
        .write_data(rs2_data),
        .read_data(mem_read_data)
    );

    wire [31:0] rf_wd = is_lw ? mem_read_data : alu_out;

    regfile rf (
        .clk(clk),
        .we(reg_we),
        .rs1_addr(rs1),
        .rs2_addr(rs2),
        .rd_addr(rd),
        .rd_data(rf_wd),
        .rs1_data(rs1_data),
        .rs2_data(rs2_data)
    );

    wire [31:0] alu_out;
    wire [31:0] alu_b = (opcode == 7'b0010011 || is_lw || is_sw) ? imm : rs2_data;
    /* verilator lint_off UNUSEDSIGNAL */
    wire alu_zero;
    /* verilator lint_on UNUSEDSIGNAL */
    alu my_alu (
        .a(rs1_data),
        .b(alu_b),
        .alu_op(4'b0000),
        .result(alu_out),
        .zero(alu_zero)
    );

    assign debug_pc = pc;
    assign debug_instr = instr;
    assign debug_alu_out = alu_out;

endmodule

waves/top.vcd
$version Generated by VerilatedVcd $end
$timescale 1ps $end
 $scope module TOP $end
  $var wire 1 I clk $end
  $var wire 1 J rst_n $end
  $var wire 32 K debug_pc [31:0] $end
  $var wire 32 L debug_instr [31:0] $end
  $var wire 32 M debug_alu_out [31:0] $end
  $scope module top $end
   $var wire 1 I clk $end
   $var wire 1 J rst_n $end
   $var wire 32 K debug_pc [31:0] $end
   $var wire 32 L debug_instr [31:0] $end
   $var wire 32 M debug_alu_out [31:0] $end
   $var wire 32 N pc [31:0] $end
   $var wire 32 L instr [31:0] $end
   $var wire 7 O opcode [6:0] $end
   $var wire 5 P rd [4:0] $end
   $var wire 5 Q rs1 [4:0] $end
   $var wire 5 R rs2 [4:0] $end
   $var wire 32 S rs1_data [31:0] $end
   $var wire 32 F rs2_data [31:0] $end
   $var wire 32 T imm_i [31:0] $end
   $var wire 32 U imm_s [31:0] $end
   $var wire 32 V imm [31:0] $end
   $var wire 1 W is_lw $end
   $var wire 1 X is_sw $end
   $var wire 1 Y reg_we $end
   $var wire 32 Z mem_read_data [31:0] $end
   $var wire 32 [ rf_wd [31:0] $end
   $var wire 32 G alu_out [31:0] $end
   $var wire 32 \ alu_b [31:0] $end
   $var wire 1 H alu_zero $end
   $scope module data_mem $end
    $var wire 1 I clk $end
    $var wire 1 X we $end
    $var wire 32 G addr [31:0] $end
    $var wire 32 F write_data [31:0] $end
    $var wire 32 Z read_data [31:0] $end
    $var wire 32 # i [31:0] $end
   $upscope $end
   $scope module inst_mem $end
    $var wire 1 I clk $end
    $var wire 1 ] we $end
    $var wire 32 N addr [31:0] $end
    $var wire 32 ^ write_data [31:0] $end
    $var wire 32 L read_data [31:0] $end
    $var wire 32 $ i [31:0] $end
   $upscope $end
   $scope module my_alu $end
    $var wire 32 S a [31:0] $end
    $var wire 32 \ b [31:0] $end
    $var wire 4 _ alu_op [3:0] $end
    $var wire 32 G result [31:0] $end
    $var wire 1 H zero $end
   $upscope $end
   $scope module rf $end
    $var wire 1 I clk $end
    $var wire 1 Y we $end
    $var wire 5 Q rs1_addr [4:0] $end
    $var wire 5 R rs2_addr [4:0] $end
    $var wire 5 P rd_addr [4:0] $end
    $var wire 32 [ rd_data [31:0] $end
    $var wire 32 S rs1_data [31:0] $end
    $var wire 32 F rs2_data [31:0] $end
    $var wire 32 & regs[0] [31:0] $end
    $var wire 32 ' regs[1] [31:0] $end
    $var wire 32 ( regs[2] [31:0] $end
    $var wire 32 ) regs[3] [31:0] $end
    $var wire 32 * regs[4] [31:0] $end
    $var wire 32 + regs[5] [31:0] $end
    $var wire 32 , regs[6] [31:0] $end
    $var wire 32 - regs[7] [31:0] $end
    $var wire 32 . regs[8] [31:0] $end
    $var wire 32 / regs[9] [31:0] $end
    $var wire 32 0 regs[10] [31:0] $end
    $var wire 32 1 regs[11] [31:0] $end
    $var wire 32 2 regs[12] [31:0] $end
    $var wire 32 3 regs[13] [31:0] $end
    $var wire 32 4 regs[14] [31:0] $end
    $var wire 32 5 regs[15] [31:0] $end
    $var wire 32 6 regs[16] [31:0] $end
    $var wire 32 7 regs[17] [31:0] $end
    $var wire 32 8 regs[18] [31:0] $end
    $var wire 32 9 regs[19] [31:0] $end
    $var wire 32 : regs[20] [31:0] $end
    $var wire 32 ; regs[21] [31:0] $end
    $var wire 32 < regs[22] [31:0] $end
    $var wire 32 = regs[23] [31:0] $end
    $var wire 32 > regs[24] [31:0] $end
    $var wire 32 ? regs[25] [31:0] $end
    $var wire 32 @ regs[26] [31:0] $end
    $var wire 32 A regs[27] [31:0] $end
    $var wire 32 B regs[28] [31:0] $end
    $var wire 32 C regs[29] [31:0] $end
    $var wire 32 D regs[30] [31:0] $end
    $var wire 32 E regs[31] [31:0] $end
    $var wire 32 % i [31:0] $end
   $upscope $end
  $upscope $end
 $upscope $end
$enddefinitions $end


#0
b00000000000000000000010000000000 #
b00000000000000000000010000000000 $
b00000000000000000000000000100000 %
b00000000000000000000000000000000 &
b00000000000000000000000000000000 '
b00000000000000000000000000000000 (
b00000000000000000000000000000000 )
b00000000000000000000000000000000 *
b00000000000000000000000000000000 +
b00000000000000000000000000000000 ,
b00000000000000000000000000000000 -
b00000000000000000000000000000000 .
b00000000000000000000000000000000 /
b00000000000000000000000000000000 0
b00000000000000000000000000000000 1
b00000000000000000000000000000000 2
b00000000000000000000000000000000 3
b00000000000000000000000000000000 4
b00000000000000000000000000000000 5
b00000000000000000000000000000000 6
b00000000000000000000000000000000 7
b00000000000000000000000000000000 8
b00000000000000000000000000000000 9
b00000000000000000000000000000000 :
b00000000000000000000000000000000 ;
b00000000000000000000000000000000 <
b00000000000000000000000000000000 =
b00000000000000000000000000000000 >
b00000000000000000000000000000000 ?
b00000000000000000000000000000000 @
b00000000000000000000000000000000 A
b00000000000000000000000000000000 B
b00000000000000000000000000000000 C
b00000000000000000000000000000000 D
b00000000000000000000000000000000 E
b00000000000000000000000000000000 F
b00000000000000000000000000010000 G
0H
0I
0J
b00000000000000000000000000000000 K
b00000001000000000000000010010011 L
b00000000000000000000000000010000 M
b00000000000000000000000000000000 N
b0010011 O
b00001 P
b00000 Q
b10000 R
b00000000000000000000000000000000 S
b00000000000000000000000000010000 T
b00000000000000000000000000000001 U
b00000000000000000000000000010000 V
0W
0X
1Y
b00000000000000000000000000000000 Z
b00000000000000000000000000010000 [
b00000000000000000000000000010000 \
0]
b00000000000000000000000000000000 ^
b0000 _
#1
b00000000000000000000000000010000 '
1I
#2
0I
#3
1I
#4
0I
1J
#5
b00000000000000000000000001100100 G
1I
b00000000000000000000000000000100 K
b00000110010000000000000100010011 L
b00000000000000000000000001100100 M
b00000000000000000000000000000100 N
b00010 P
b00100 R
b00000000000000000000000001100100 T
b00000000000000000000000001100010 U
b00000000000000000000000001100100 V
b00000000000000000000000001100100 [
b00000000000000000000000001100100 \
#6
0I
#7
b00000000000000000000000001100100 (
b00000000000000000000000001100100 F
b00000000000000000000000000010000 G
1I
b00000000000000000000000000001000 K
b00000000001000001010000000100011 L
b00000000000000000000000000010000 M
b00000000000000000000000000001000 N
b0100011 O
b00000 P
b00001 Q
b00010 R
b00000000000000000000000000010000 S
b00000000000000000000000000000010 T
b00000000000000000000000000000000 U
b00000000000000000000000000000000 V
1X
0Y
b00000000000000000000000000010000 [
b00000000000000000000000000000000 \
#8
0I
#9
b00000000000000000000000000000000 F
1I
b00000000000000000000000000001100 K
b00000000000000001010000110000011 L
b00000000000000000000000000001100 N
b0000011 O
b00011 P
b00000 R
b00000000000000000000000000000000 T
b00000000000000000000000000000011 U
1W
0X
1Y
b00000000000000000000000001100100 Z
b00000000000000000000000001100100 [
#10
0I
#11
b00000000000000000000000001100100 )
b00000000000000000000000000000000 G
1H
1I
b00000000000000000000000000010000 K
b00000000000000000000000000000000 L
b00000000000000000000000000000000 M
b00000000000000000000000000010000 N
b0000000 O
b00000 P
b00000 Q
b00000000000000000000000000000000 S
b00000000000000000000000000000000 U
0W
0Y
b00000001000000000000000010010011 Z
b00000000000000000000000000000000 [
#12
0I
#13
1I
b00000000000000000000000000010100 K
b00000000000000000000000000010100 N
#14
0I
#15
1I
b00000000000000000000000000011000 K
b00000000000000000000000000011000 N
#16
0I
#17
1I
b00000000000000000000000000011100 K
b00000000000000000000000000011100 N
#18
0I
#19
1I
b00000000000000000000000000100000 K
b00000000000000000000000000100000 N
#20
0I
#21
1I
b00000000000000000000000000100100 K
b00000000000000000000000000100100 N
#22
0I
#23
1I
b00000000000000000000000000101000 K
b00000000000000000000000000101000 N
