hardware/include/defines.v
`define ALU_ADD 4'b0000
`define ALU_SUB 4`b1000
`define ALU_SLL 4'b0001
`define ALU_SLT 4'b0010
`define ALU_SLTU 4'b0011
`define ALU_XOR 4'b1000
`define ALU_SRL 4'b0101
`define ALU_SRA 4'b1101
`define ALU_OR   4'b0110
`define ALU_AND  4'b0111

hardware/src/alu.v
`include "defines.v"

module alu (
    input wire [31:0] a,
    input wire [31:0] b,
    input wire [3:0] alu_op,
    output reg [31:0] result,
    output wire zero
);

    assign zero = (result == 32'b0);

    always @(*) begin
        case (alu_op)
            `ALU_ADD: result = a + b;
            `ALU_SUB: result = a - b;
            `ALU_AND: result = a & b;
            `ALU_OR: result = a | b;
            `ALU_XOR: result = a ^ b;
            `ALU_SLL: result = a << b[4:0];
            `ALU_SRL: result = a >> b[4:0];
            `ALU_SRA: result = $signed(a) >>> b [4:0] ;
            `ALU_SLT: result = ($signed(a) < $signed(b)) ? 32'b1 : 32'b0;
            `ALU_SLTU: result = (a < b) ? 32'b1 : 32'b0;
            default: result = 32'b0;
        endcase
    end
    
endmodule

hardware/src/regfile.v
module regfile (
    input wire clk,
    input wire we,
    input wire [4:0] rs1_addr,
    input wire [4:0] rs2_addr,
    input wire [4:0] rd_addr,
    input wire [31:0] rd_data,
    output wire [31:0] rs1_data,
    output wire [31:0] rs2_data
);
    reg [31:0] regs [31:0];

    assign rs1_data = (rs1_addr == 5'b0) ? 32'b0 : regs[rs1_addr];
    assign rs2_data = (rs2_addr == 5'b0) ? 32'b0 : regs[rs2_addr];

    integer i;
    initial begin
        for (i = 0; i < 32; i = i + 1) regs[i] = 32'b0;
    end

    always @(posedge clk) begin
        if (we && (rd_addr != 5'b0)) begin
            regs[rd_addr] <= rd_data;
        end
    end

endmodule

hardware/src/memory.v
module memory (
    input wire clk,
    input wire [3:0] be,
    /* verilator lint_off UNUSEDSIGNAL */
    input wire [31:0] addr,
    /* verilator lint_off UNUSEDSIGNAL */
    input wire [31:0] write_data,
    output wire [31:0] read_data
);
    reg [31:0] ram [1023:0];

    assign read_data = ram[addr[11:2]];

    always @(posedge clk) begin
        if (be[0]) ram[addr[11:2]][7:0]   <= write_data[7:0];
        if (be[1]) ram[addr[11:2]][15:8]  <= write_data[15:8];
        if (be[2]) ram[addr[11:2]][23:16] <= write_data[23:16];
        if (be[3]) ram[addr[11:2]][31:24] <= write_data[31:24];
    end

    integer i;
    initial begin
        for (i = 0; i < 1024; i = i + 1) begin
            ram[i] = 32'b0;
        end
        $readmemh("machine_code.txt", ram);
    end
    
endmodule

hardware/src/top.v
`include "defines.v"
module top (
    input wire clk,
    input wire rst_n,
    output wire [31:0] debug_pc,
    output wire [31:0] debug_instr,
    output wire [31:0] debug_alu_out
);
    reg [31:0] pc;

    /* verilator lint_off UNUSEDSIGNAL */
    wire [31:0] instr;
    /* verilator lint_on UNUSEDSIGNAL */

    memory inst_mem (
        .clk(clk),
        .be(4'b0000),
        .addr(pc),
        .write_data(32'b0),
        .read_data(instr)
    );

    wire [6:0] opcode = instr[6:0];
    wire [4:0] rd     = instr[11:7];
    wire [4:0] rs1    = instr[19:15];
    wire [4:0] rs2    = instr[24:20];
    wire [2:0] funct3 = instr[14:12];
    /* verilator lint_off UNUSEDSIGNAL */
    wire [6:0] funct7 = instr[31:25];
    /* verilator lint_on UNUSEDSIGNAL */

    wire [31:0] rs1_data, rs2_data;

    localparam OP_I_ALU  = 7'b0010011;
    localparam OP_I_LOAD = 7'b0000011;
    localparam OP_S_TYPE = 7'b0100011;
    localparam OP_B_TYPE = 7'b1100011;
    localparam OP_R_TYPE = 7'b0110011;
    localparam OP_LUI    = 7'b0110111;
    localparam OP_AUIPC  = 7'b0010111;
    localparam OP_JAL    = 7'b1101111;
    localparam OP_JALR = 7'b1100111;

    wire [31:0] imm_i = {{20{instr[31]}}, instr[31:20]};
    wire [31:0] imm_s = {{20{instr[31]}}, instr[31:25], instr[11:7]};
    wire [31:0] imm_b = {{20{instr[31]}}, instr[7], instr[30:25], instr[11:8], 1'b0};
    wire [31:0] imm_u = {instr[31:12], 12'b0};
    wire [31:0] imm_j = {{12{instr[31]}}, instr[19:12], instr[20], instr[30:21], 1'b0};

    reg [31:0] imm;
    always @(*) begin
        case (opcode)
            OP_I_ALU, OP_I_LOAD, OP_JALR: imm = imm_i;
            OP_S_TYPE:           imm = imm_s;
            OP_B_TYPE:           imm = imm_b;
            OP_LUI, OP_AUIPC:    imm = imm_u;
            OP_JAL:              imm = imm_j;
            default: imm = 32'b0;
        endcase
    end
    
    wire is_jal = (opcode == OP_JAL);
    wire is_beq = (opcode == OP_B_TYPE);
    wire is_jalr = (opcode == OP_JALR);

    reg branch_condition;
    always @(*) begin
        case (funct3)
            3'b000: branch_condition = alu_zero;
            3'b001: branch_condition = !alu_zero;
            3'b100: branch_condition = alu_out[0];
            3'b101: branch_condition = !alu_out[0];
            3'b110: branch_condition = alu_out[0];
            3'b111: branch_condition = !alu_out[0];
            default: branch_condition = 1'b0;
        endcase
    end

    wire take_branch = (is_beq && branch_condition) || is_jal || is_jalr;

    wire [31:0] jump_base   = is_jalr ? rs1_data : pc;
    wire [31:0] jump_offset = is_jal  ? imm_j    : is_jalr ? imm_i : imm_b;

    wire [31:0] pc_next;
    wire [31:0] pc_target_raw = $unsigned($signed(jump_base) + $signed(jump_offset));
    wire [31:0] pc_target     = is_jalr ? (pc_target_raw & 32'hfffffffe) : pc_target_raw;
    wire [31:0] pc_plus4 = pc + 4;

    assign pc_next = take_branch ? pc_target : pc_plus4;

    always @(posedge clk or negedge rst_n) begin
        if (!rst_n) begin
            pc <= 32'b0;
        end
        else begin
            pc <= pc_next;
        end
    end

    wire is_lw = (opcode == OP_I_LOAD);
    wire is_sw = (opcode == OP_S_TYPE);
    wire reg_we = (opcode == OP_I_ALU || opcode == OP_R_TYPE || is_lw || 
               opcode == OP_LUI || opcode == OP_AUIPC || is_jal || is_jalr);
    

    reg [31:0] mem_write_data;
    always @(*) begin
        case (funct3)
            3'b000: mem_write_data = {4{rs2_data[7:0]}};
            3'b001: mem_write_data = {2{rs2_data[15:0]}};
            3'b010: mem_write_data = rs2_data;
            default: mem_write_data = rs2_data;
        endcase
    end

    reg [3:0] mem_be;
    always @(*) begin
        if (is_sw) begin
            case (funct3)
                3'b000: mem_be = 4'b0001 << alu_out[1:0];
                3'b001: mem_be = 4'b0011 << alu_out[1:0];
                3'b010: mem_be = 4'b1111;
                default: mem_be = 4'b0000;
            endcase
        end
        else begin
            mem_be = 4'b0000;
        end
    end

    wire [31:0] mem_read_data;
    memory data_mem (
        .clk(clk),
        .be(mem_be),
        .addr(alu_out),
        .write_data(mem_write_data),
        .read_data(mem_read_data)
    );

    reg [31:0] mem_data_ext;
    always @(*) begin
        case (funct3)
            3'b000: mem_data_ext = {{24{mem_read_data[7]}}, mem_read_data[7:0]};
            3'b001: mem_data_ext = {{16{mem_read_data[15]}}, mem_read_data[15:0]};
            3'b010: mem_data_ext = mem_read_data;
            3'b100: mem_data_ext = {24'b0, mem_read_data[7:0]};
            3'b101: mem_data_ext = {16'b0, mem_read_data[15:0]};
            default: mem_data_ext = mem_read_data;
        endcase
    end

    /* verilator lint_off UNOPTFLAT */
    wire [31:0] rf_wd = (opcode == OP_I_LOAD) ? mem_data_ext : 
                        (is_jal || is_jalr)   ? pc_plus4 : 
                        (opcode == OP_LUI)    ? imm_u :
                        alu_out;
    /* verilator lint_on UNOPTFLAT */

    regfile rf (
        .clk(clk),
        .we(reg_we),
        .rs1_addr(rs1),
        .rs2_addr(rs2),
        .rd_addr(rd),
        .rd_data(rf_wd),
        .rs1_data(rs1_data),
        .rs2_data(rs2_data)
    );

    reg [3:0] alu_ctrl; 
    always @(*) begin
        case (opcode)
            OP_R_TYPE: begin
                case (funct3)
                    3'b000: alu_ctrl = funct7[5] ? `ALU_SUB : `ALU_ADD;
                    3'b101: alu_ctrl = funct7[5] ? `ALU_SRA : `ALU_SRL;
                    default: alu_ctrl = {1'b0, funct3};
                endcase
            end

            OP_I_ALU:begin
                if (funct3 == 3'b101 && funct7[5]) begin
                    alu_ctrl = `ALU_SRA;
                end
                else if (funct3 == 3'b001)
                    alu_ctrl = `ALU_SLL;
                else if (funct3 == 3'b101)
                    alu_ctrl = `ALU_SRL;
                else begin
                    alu_ctrl = {1'b0, funct3};
                end
            end

            OP_B_TYPE: begin
                case (funct3)
                    3'b000, 3'b001: alu_ctrl = `ALU_SUB;
                    3'b100, 3'b101: alu_ctrl = `ALU_SLT;
                    3'b110, 3'b111: alu_ctrl = `ALU_SLTU;
                    default: alu_ctrl = `ALU_SUB;
                endcase
            end

            OP_JALR: alu_ctrl = `ALU_ADD;
            default: alu_ctrl = `ALU_ADD;
        endcase
    end

    wire [31:0] alu_out;
    wire use_imm = (opcode == OP_I_ALU || opcode == OP_I_LOAD || opcode == OP_S_TYPE || opcode == OP_LUI || opcode == OP_AUIPC);
    wire [31:0] alu_a = (opcode == OP_AUIPC) ? pc : (opcode == OP_LUI)   ? 32'b0 : rs1_data;
    wire [31:0] alu_b = use_imm ? imm : rs2_data;

    /* verilator lint_off UNUSEDSIGNAL */
    wire alu_zero;
    /* verilator lint_on UNUSEDSIGNAL */

    alu my_alu (
        .a(alu_a),
        .b(alu_b),
        .alu_op(alu_ctrl),
        .result(alu_out),
        .zero(alu_zero)
    );

    assign debug_pc = pc;
    assign debug_instr = instr;
    assign debug_alu_out = alu_out;

endmodule

waves/top.vcd
$version Generated by VerilatedVcd $end
$timescale 1ps $end
 $scope module TOP $end
  $var wire 1 W clk $end
  $var wire 1 X rst_n $end
  $var wire 32 Y debug_pc [31:0] $end
  $var wire 32 Z debug_instr [31:0] $end
  $var wire 32 [ debug_alu_out [31:0] $end
  $scope module top $end
   $var wire 1 W clk $end
   $var wire 1 X rst_n $end
   $var wire 32 Y debug_pc [31:0] $end
   $var wire 32 Z debug_instr [31:0] $end
   $var wire 32 [ debug_alu_out [31:0] $end
   $var wire 32 F pc [31:0] $end
   $var wire 32 Z instr [31:0] $end
   $var wire 7 \ opcode [6:0] $end
   $var wire 5 ] rd [4:0] $end
   $var wire 5 ^ rs1 [4:0] $end
   $var wire 5 _ rs2 [4:0] $end
   $var wire 3 ` funct3 [2:0] $end
   $var wire 7 a funct7 [6:0] $end
   $var wire 32 M rs1_data [31:0] $end
   $var wire 32 N rs2_data [31:0] $end
   $var wire 7 s OP_I_ALU [6:0] $end
   $var wire 7 t OP_I_LOAD [6:0] $end
   $var wire 7 u OP_S_TYPE [6:0] $end
   $var wire 7 v OP_B_TYPE [6:0] $end
   $var wire 7 w OP_R_TYPE [6:0] $end
   $var wire 7 x OP_LUI [6:0] $end
   $var wire 7 y OP_AUIPC [6:0] $end
   $var wire 7 z OP_JAL [6:0] $end
   $var wire 7 { OP_JALR [6:0] $end
   $var wire 32 G imm_i [31:0] $end
   $var wire 32 b imm_s [31:0] $end
   $var wire 32 H imm_b [31:0] $end
   $var wire 32 c imm_u [31:0] $end
   $var wire 32 I imm_j [31:0] $end
   $var wire 32 J imm [31:0] $end
   $var wire 1 d is_jal $end
   $var wire 1 e is_beq $end
   $var wire 1 f is_jalr $end
   $var wire 1 g branch_condition $end
   $var wire 1 h take_branch $end
   $var wire 32 i jump_base [31:0] $end
   $var wire 32 j jump_offset [31:0] $end
   $var wire 32 k pc_next [31:0] $end
   $var wire 32 O pc_target_raw [31:0] $end
   $var wire 32 l pc_target [31:0] $end
   $var wire 32 K pc_plus4 [31:0] $end
   $var wire 1 m is_lw $end
   $var wire 1 n is_sw $end
   $var wire 1 o reg_we $end
   $var wire 32 P mem_write_data [31:0] $end
   $var wire 4 Q mem_be [3:0] $end
   $var wire 32 R mem_read_data [31:0] $end
   $var wire 32 p mem_data_ext [31:0] $end
   $var wire 32 q rf_wd [31:0] $end
   $var wire 4 L alu_ctrl [3:0] $end
   $var wire 32 S alu_out [31:0] $end
   $var wire 1 r use_imm $end
   $var wire 32 T alu_a [31:0] $end
   $var wire 32 U alu_b [31:0] $end
   $var wire 1 V alu_zero $end
   $scope module data_mem $end
    $var wire 1 W clk $end
    $var wire 4 Q be [3:0] $end
    $var wire 32 S addr [31:0] $end
    $var wire 32 P write_data [31:0] $end
    $var wire 32 R read_data [31:0] $end
    $var wire 32 # i [31:0] $end
   $upscope $end
   $scope module inst_mem $end
    $var wire 1 W clk $end
    $var wire 4 | be [3:0] $end
    $var wire 32 F addr [31:0] $end
    $var wire 32 } write_data [31:0] $end
    $var wire 32 Z read_data [31:0] $end
    $var wire 32 $ i [31:0] $end
   $upscope $end
   $scope module my_alu $end
    $var wire 32 T a [31:0] $end
    $var wire 32 U b [31:0] $end
    $var wire 4 L alu_op [3:0] $end
    $var wire 32 S result [31:0] $end
    $var wire 1 V zero $end
   $upscope $end
   $scope module rf $end
    $var wire 1 W clk $end
    $var wire 1 o we $end
    $var wire 5 ^ rs1_addr [4:0] $end
    $var wire 5 _ rs2_addr [4:0] $end
    $var wire 5 ] rd_addr [4:0] $end
    $var wire 32 q rd_data [31:0] $end
    $var wire 32 M rs1_data [31:0] $end
    $var wire 32 N rs2_data [31:0] $end
    $var wire 32 & regs[0] [31:0] $end
    $var wire 32 ' regs[1] [31:0] $end
    $var wire 32 ( regs[2] [31:0] $end
    $var wire 32 ) regs[3] [31:0] $end
    $var wire 32 * regs[4] [31:0] $end
    $var wire 32 + regs[5] [31:0] $end
    $var wire 32 , regs[6] [31:0] $end
    $var wire 32 - regs[7] [31:0] $end
    $var wire 32 . regs[8] [31:0] $end
    $var wire 32 / regs[9] [31:0] $end
    $var wire 32 0 regs[10] [31:0] $end
    $var wire 32 1 regs[11] [31:0] $end
    $var wire 32 2 regs[12] [31:0] $end
    $var wire 32 3 regs[13] [31:0] $end
    $var wire 32 4 regs[14] [31:0] $end
    $var wire 32 5 regs[15] [31:0] $end
    $var wire 32 6 regs[16] [31:0] $end
    $var wire 32 7 regs[17] [31:0] $end
    $var wire 32 8 regs[18] [31:0] $end
    $var wire 32 9 regs[19] [31:0] $end
    $var wire 32 : regs[20] [31:0] $end
    $var wire 32 ; regs[21] [31:0] $end
    $var wire 32 < regs[22] [31:0] $end
    $var wire 32 = regs[23] [31:0] $end
    $var wire 32 > regs[24] [31:0] $end
    $var wire 32 ? regs[25] [31:0] $end
    $var wire 32 @ regs[26] [31:0] $end
    $var wire 32 A regs[27] [31:0] $end
    $var wire 32 B regs[28] [31:0] $end
    $var wire 32 C regs[29] [31:0] $end
    $var wire 32 D regs[30] [31:0] $end
    $var wire 32 E regs[31] [31:0] $end
    $var wire 32 % i [31:0] $end
   $upscope $end
  $upscope $end
 $upscope $end
$enddefinitions $end


#0
b00000000000000000000010000000000 #
b00000000000000000000010000000000 $
b00000000000000000000000000100000 %
b00000000000000000000000000000000 &
b00000000000000000000000000000000 '
b00000000000000000000000000000000 (
b00000000000000000000000000000000 )
b00000000000000000000000000000000 *
b00000000000000000000000000000000 +
b00000000000000000000000000000000 ,
b00000000000000000000000000000000 -
b00000000000000000000000000000000 .
b00000000000000000000000000000000 /
b00000000000000000000000000000000 0
b00000000000000000000000000000000 1
b00000000000000000000000000000000 2
b00000000000000000000000000000000 3
b00000000000000000000000000000000 4
b00000000000000000000000000000000 5
b00000000000000000000000000000000 6
b00000000000000000000000000000000 7
b00000000000000000000000000000000 8
b00000000000000000000000000000000 9
b00000000000000000000000000000000 :
b00000000000000000000000000000000 ;
b00000000000000000000000000000000 <
b00000000000000000000000000000000 =
b00000000000000000000000000000000 >
b00000000000000000000000000000000 ?
b00000000000000000000000000000000 @
b00000000000000000000000000000000 A
b00000000000000000000000000000000 B
b00000000000000000000000000000000 C
b00000000000000000000000000000000 D
b00000000000000000000000000000000 E
b00000000000000000000000000000000 F
b00000000000000000000000000001010 G
b00000000000000000000100000000100 H
b00000000000000000000000000001010 I
b00000000000000000000000000001010 J
b00000000000000000000000000000100 K
b0000 L
b00000000000000000000000000000000 M
b00000000000000000000000000000000 N
b00000000000000000000100000000100 O
b00000000000000000000000000000000 P
b0000 Q
b00000000001000101101010010010011 R
b00000000000000000000000000001010 S
b00000000000000000000000000000000 T
b00000000000000000000000000001010 U
0V
0W
0X
b00000000000000000000000000000000 Y
b00000000101000000000001010010011 Z
b00000000000000000000000000001010 [
b0010011 \
b00101 ]
b00000 ^
b01010 _
b000 `
b0000000 a
b00000000000000000000000000000101 b
b00000000101000000000000000000000 c
0d
0e
0f
0g
0h
b00000000000000000000000000000000 i
b00000000000000000000100000000100 j
b00000000000000000000000000000100 k
b00000000000000000000100000000100 l
0m
0n
1o
b11111111111111111111111110010011 p
b00000000000000000000000000001010 q
1r
b0010011 s
b0000011 t
b0100011 u
b1100011 v
b0110011 w
b0110111 x
b0010111 y
b1101111 z
b1100111 {
b0000 |
b00000000000000000000000000000000 }
#1
b00000000000000000000000000001010 +
1W
#2
0W
#3
1W
#4
1X
#5
0W
#6
b00000000000000000000000000000100 F
b00000000000000000000000000000000 G
b00000000000000000000000000000110 H
b00000000000000000000000000000000 I
b00000000000000000000000000000000 J
b00000000000000000000000000001000 K
b00000000000000000000000000001010 O
b00000000000000000000001100010111 R
b00000000000000000000000000000100 S
b00000000000000000000000000000100 T
b00000000000000000000000000000000 U
1W
b00000000000000000000000000000100 Y
b00000000000000000000001100010111 Z
b00000000000000000000000000000100 [
b0010111 \
b00110 ]
b00000 _
b00000000000000000000000000000110 b
b00000000000000000000000000000000 c
b00000000000000000000000000000100 i
b00000000000000000000000000000110 j
b00000000000000000000000000001000 k
b00000000000000000000000000001010 l
b00000000000000000000000000010111 p
b00000000000000000000000000000100 q
#7
0W
#8
b00000000000000000000000000000100 ,
b00000000000000000000000000001000 F
b00000000000000000000000000000010 G
b00000000000000000000100000001000 H
b00000000000000101101000000000010 I
b00000000000000000000000000000010 J
b00000000000000000000000000001100 K
b0101 L
b00000000000000000000000000001010 M
b00000000000000000000100000010000 O
b00000000101000000000001010010011 R
b00000000000000000000000000000010 S
b00000000000000000000000000001010 T
b00000000000000000000000000000010 U
1W
b00000000000000000000000000001000 Y
b00000000001000101101010010010011 Z
b00000000000000000000000000000010 [
b0010011 \
b01001 ]
b00101 ^
b00010 _
b101 `
b00000000000000000000000000001001 b
b00000000001000101101000000000000 c
1g
b00000000000000000000000000001000 i
b00000000000000000000100000001000 j
b00000000000000000000000000001100 k
b00000000000000000000100000010000 l
b00000000000000000000001010010011 p
b00000000000000000000000000000010 q
#9
0W
#10
b00000000000000000000000000000010 /
b00000000000000000000000000001100 F
b00000000000000000000010000000010 G
b00000000000000000000010000001010 H
b00000000000000101101010000000010 I
b00000000000000000000010000000010 J
b00000000000000000000000000010000 K
b1101 L
b00000000000000000000010000010110 O
b00000000000000000000010000000010 U
1W
b00000000000000000000000000001100 Y
b01000000001000101101010100010011 Z
b01010 ]
b0100000 a
b00000000000000000000010000001010 b
b01000000001000101101000000000000 c
b00000000000000000000000000001100 i
b00000000000000000000010000001010 j
b00000000000000000000000000010000 k
b00000000000000000000010000010110 l
#11
0W
#12
b00000000000000000000000000000010 0
b00000000000000000000000000010000 F
b00000000000000000000000000000000 G
b00000000000000000000000000001100 H
b00000000000000000000000000000000 I
b00000000000000000000000000000000 J
b00000000000000000000000000010100 K
b0000 L
b00000000000000000000000000000000 M
b00000000000000000000000000011100 O
b00000000000000000000000000000000 S
b00000000000000000000000000000000 T
b00000000000000000000000000000000 U
1V
1W
b00000000000000000000000000010000 Y
b00000000000000000000011000110111 Z
b00000000000000000000000000000000 [
b0110111 \
b01100 ]
b00000 ^
b00000 _
b000 `
b0000000 a
b00000000000000000000000000001100 b
b00000000000000000000000000000000 c
b00000000000000000000000000010000 i
b00000000000000000000000000001100 j
b00000000000000000000000000010100 k
b00000000000000000000000000011100 l
b11111111111111111111111110010011 p
b00000000000000000000000000000000 q
#13
0W
#14
b00000000000000000000000000010100 F
b00000000000000000000000001000000 G
b00000000000000000000000001001100 H
b00000000000001100000000001000000 I
b00000000000000000000000001000000 J
b00000000000000000000000000011000 K
b00000000000000000000000001100000 O
b00000000000000000000000000000000 R
b00000000000000000000000001000000 S
b00000000000000000000000001000000 U
0V
1W
b00000000000000000000000000010100 Y
b00000100000001100000011000010011 Z
b00000000000000000000000001000000 [
b0010011 \
b01100 ^
b0000010 a
b00000000000000000000000001001100 b
b00000100000001100000000000000000 c
0g
b00000000000000000000000000010100 i
b00000000000000000000000001001100 j
b00000000000000000000000000011000 k
b00000000000000000000000001100000 l
b00000000000000000000000000000000 p
b00000000000000000000000001000000 q
#15
0W
#16
b00000000000000000000000001000000 2
b00000000000000000000000000011000 F
b11111111111111111111111111111001 G
b11111111111111111111111111101100 H
b11111111111100000000111111111000 I
b11111111111111111111111111111001 J
b00000000000000000000000000011100 K
b00000000000000000000000000000100 O
b11111111111111111111111111111001 S
b11111111111111111111111111111001 U
1W
b00000000000000000000000000011000 Y
b11111111100100000000011010010011 Z
b11111111111111111111111111111001 [
b01101 ]
b00000 ^
b11001 _
b1111111 a
b11111111111111111111111111101101 b
b11111111100100000000000000000000 c
b00000000000000000000000000011000 i
b11111111111111111111111111101100 j
b00000000000000000000000000011100 k
b00000000000000000000000000000100 l
b11111111111111111111111111111001 q
#17
0W
#18
b11111111111111111111111111111001 3
b00000000000000000000000000011100 F
b00000000000000000000000000001101 G
b00000000000000000000000000000000 H
b00000000000001100000100000001100 I
b00000000000000000000000000000000 J
b00000000000000000000000000100000 K
b00000000000000000000000001000000 M
b11111111111111111111111111111001 N
b00000000000000000000000000011100 O
b11111001111110011111100111111001 P
b0001 Q
b00000000000000000000000001000000 S
b00000000000000000000000001000000 T
b00000000000000000000000000000000 U
1W
b00000000000000000000000000011100 Y
b00000000110101100000000000100011 Z
b00000000000000000000000001000000 [
b0100011 \
b00000 ]
b01100 ^
b01101 _
b0000000 a
b00000000000000000000000000000000 b
b00000000110101100000000000000000 c
b00000000000000000000000000011100 i
b00000000000000000000000000000000 j
b00000000000000000000000000100000 k
b00000000000000000000000000011100 l
1n
0o
b00000000000000000000000001000000 q
#19
0W
#20
b00000000000000000000000000100000 F
b00000000000000000000000000000000 G
b00000000000000000000000000001110 H
b00000000000001100000000000000000 I
b00000000000000000000000000100100 K
b00000000000000000000000000000000 N
b00000000000000000000000000101110 O
b00000000000000000000000000000000 P
b0000 Q
b00000000000000000000000011111001 R
1W
b00000000000000000000000000100000 Y
b00000000000001100000011100000011 Z
b0000011 \
b01110 ]
b00000 _
b00000000000000000000000000001110 b
b00000000000001100000000000000000 c
b00000000000000000000000000100000 i
b00000000000000000000000000001110 j
b00000000000000000000000000100100 k
b00000000000000000000000000101110 l
1m
0n
1o
b11111111111111111111111111111001 p
b11111111111111111111111111111001 q
#21
0W
#22
b11111111111111111111111111111001 4
b00000000000000000000000000100100 F
b00000000000000000000000000000101 G
b00000000000000000000000000001100 H
b00000000000000101000100000000100 I
b00000000000000000000000000001100 J
b00000000000000000000000000101000 K
b1000 L
b00000000000000000000000000001010 M
b00000000000000000000000000001010 N
b00000000000000000000000000110000 O
b00001010000010100000101000001010 P
b00000000101000000000001010010011 R
b00000000000000000000000000000000 S
b00000000000000000000000000001010 T
b00000000000000000000000000001010 U
1V
1W
b00000000000000000000000000100100 Y
b00000000010100101000011001100011 Z
b00000000000000000000000000000000 [
b1100011 \
b01100 ]
b00101 ^
b00101 _
b00000000000000000000000000001100 b
b00000000010100101000000000000000 c
1e
1g
1h
b00000000000000000000000000100100 i
b00000000000000000000000000001100 j
b00000000000000000000000000110000 k
b00000000000000000000000000110000 l
0m
0o
b11111111111111111111111110010011 p
b00000000000000000000000000000000 q
0r
#23
0W
#24
b00000000000000000000000000110000 F
b00000000000000000000000000000001 G
b00000000000000000000000000000000 H
b00000000000000000000100000000000 I
b00000000000000000000000000000000 J
b00000000000000000000000000110100 K
b0000 L
b00000000000000000000000000000000 M
b00000000000000000000000000000000 N
b00000000000000000000000000000000 P
b00000000000000000000000000000000 T
b00000000000000000000000000000000 U
1W
b00000000000000000000000000110000 Y
b00000000000100000000000001110011 Z
b1110011 \
b00000 ]
b00000 ^
b00001 _
b00000000000000000000000000000000 b
b00000000000100000000000000000000 c
0e
0h
b00000000000000000000000000110000 i
b00000000000000000000000000000000 j
b00000000000000000000000000110100 k
#25
0W
#26
b00000000000000000000000000110100 F
b00000000000000000000000000000000 G
b00000000000000000000000000000000 I
b00000000000000000000000000111000 K
b00000000000000000000000000110100 O
1W
b00000000000000000000000000110100 Y
b00000000000000000000000000000000 Z
b0000000 \
b00000 _
b00000000000000000000000000000000 c
b00000000000000000000000000110100 i
b00000000000000000000000000111000 k
b00000000000000000000000000110100 l
#27
0W
#28
b00000000000000000000000000111000 F
b00000000000000000000000000111100 K
b00000000000000000000000000111000 O
1W
b00000000000000000000000000111000 Y
b00000000000000000000000000111000 i
b00000000000000000000000000111100 k
b00000000000000000000000000111000 l
#29
0W
#30
b00000000000000000000000000111100 F
b00000000000000000000000001000000 K
b00000000000000000000000000111100 O
1W
b00000000000000000000000000111100 Y
b00000000000000000000000000111100 i
b00000000000000000000000001000000 k
b00000000000000000000000000111100 l
#31
0W
#32
b00000000000000000000000001000000 F
b00000000000000000000000001000100 K
b00000000000000000000000001000000 O
1W
b00000000000000000000000001000000 Y
b00000000000000000000000001000000 i
b00000000000000000000000001000100 k
b00000000000000000000000001000000 l
#33
0W
#34
b00000000000000000000000001000100 F
b00000000000000000000000001001000 K
b00000000000000000000000001000100 O
1W
b00000000000000000000000001000100 Y
b00000000000000000000000001000100 i
b00000000000000000000000001001000 k
b00000000000000000000000001000100 l
#35
0W
#36
b00000000000000000000000001001000 F
b00000000000000000000000001001100 K
b00000000000000000000000001001000 O
1W
b00000000000000000000000001001000 Y
b00000000000000000000000001001000 i
b00000000000000000000000001001100 k
b00000000000000000000000001001000 l
#37
0W
#38
b00000000000000000000000001001100 F
b00000000000000000000000001010000 K
b00000000000000000000000001001100 O
1W
b00000000000000000000000001001100 Y
b00000000000000000000000001001100 i
b00000000000000000000000001010000 k
b00000000000000000000000001001100 l
#39
0W
#40
b00000000000000000000000001010000 F
b00000000000000000000000001010100 K
b00000000000000000000000001010000 O
1W
b00000000000000000000000001010000 Y
b00000000000000000000000001010000 i
b00000000000000000000000001010100 k
b00000000000000000000000001010000 l
#41
0W
#42
b00000000000000000000000001010100 F
b00000000000000000000000001011000 K
b00000000000000000000000001010100 O
1W
b00000000000000000000000001010100 Y
b00000000000000000000000001010100 i
b00000000000000000000000001011000 k
b00000000000000000000000001010100 l
