hardware/include/defines.v
`define ALU_ADD 4'b0000
`define ALU_SUB 4`b1000
`define ALU_SLL 4'b0001
`define ALU_SLT 4'b0010
`define ALU_SLTU 4'b0011
`define ALU_XOR 4'b1000
`define ALU_SRL 4'b0101
`define ALU_SRA 4'b1101
`define ALU_OR   4'b0110
`define ALU_AND  4'b0111

hardware/src/alu.v
`include "defines.v"

module alu (
    input wire [31:0] a,
    input wire [31:0] b,
    input wire [3:0] alu_op,
    output reg [31:0] result,
    output wire zero
);

    assign zero = (result == 32'b0);

    always @(*) begin
        case (alu_op)
            `ALU_ADD: result = a + b;
            `ALU_SUB: result = a - b;
            `ALU_AND: result = a & b;
            `ALU_OR: result = a | b;
            `ALU_XOR: result = a ^ b;
            `ALU_SLL: result = a << b[4:0];
            `ALU_SRL: result = a >> b[4:0];
            `ALU_SRA: result = $signed(a) >>> b [4:0] ;
            `ALU_SLT: result = ($signed(a) < $signed(b)) ? 32'b1 : 32'b0;
            `ALU_SLTU: result = (a < b) ? 32'b1 : 32'b0;
            default: result = 32'b0;
        endcase
    end
    
endmodule

hardware/src/regfile.v
module regfile (
    input wire clk,
    input wire we,
    input wire [4:0] rs1_addr,
    input wire [4:0] rs2_addr,
    input wire [4:0] rd_addr,
    input wire [31:0] rd_data,
    output wire [31:0] rs1_data,
    output wire [31:0] rs2_data
);
    reg [31:0] regs [31:0];

    assign rs1_data = (rs1_addr == 5'b0) ? 32'b0 : regs[rs1_addr];
    assign rs2_data = (rs2_addr == 5'b0) ? 32'b0 : regs[rs2_addr];

    integer i;
    initial begin
        for (i = 0; i < 32; i = i + 1) regs[i] = 32'b0;
    end

    always @(posedge clk) begin
        if (we && (rd_addr != 5'b0)) begin
            regs[rd_addr] <= rd_data;
        end
    end

endmodule

hardware/src/memory.v
module memory (
    input wire clk,
    input wire we,
    /* verilator lint_off UNUSEDSIGNAL */
    input wire [31:0] addr,
    /* verilator lint_off UNUSEDSIGNAL */
    input wire [31:0] write_data,
    output wire [31:0] read_data
);
    reg [31:0] ram [1023:0];

    assign read_data = ram[addr[11:2]];

    always @(posedge clk) begin
        if (we) begin
            ram[addr[11:2]] <= write_data;
        end

    end

    integer i;
    initial begin
        for (i = 0; i < 1024; i = i + 1) begin
            ram[i] = 32'b0;
        end
        $readmemh("test.txt", ram);
    end
    
endmodule

hardware/src/top.v
module top (
    input wire clk,
    input wire rst_n,
    output wire [31:0] debug_pc,
    output wire [31:0] debug_instr,
    output wire [31:0] debug_alu_out
);
    reg [31:0] pc;
    always @(posedge clk or negedge rst_n) begin
        if (!rst_n) begin
            pc <= 32'b0;
        end
        else begin
            pc <= pc + 4;
        end
    end

    /* verilator lint_off UNUSEDSIGNAL */
    wire [31:0] instr;
    /* verilator lint_on UNUSEDSIGNAL */

    memory inst_mem (
        .clk(clk),
        .we(1'b0),
        .addr(pc),
        .write_data(32'b0),
        .read_data(instr)
    );

    wire [6:0] opcode = instr[6:0];
    wire [4:0] rd = instr[11:7];
    wire [4:0] rs1 = instr[19:15];
    wire [4:0] rs2 = instr[24:20];
    wire [31:0] imm = {{20{instr[31]}}, instr[31:20]};

    wire [31:0] rs1_data, rs2_data;
    wire reg_we = (opcode == 7'b0010011 || opcode == 7'b0110011);

    regfile rf (
        .clk(clk),
        .we(reg_we),
        .rs1_addr(rs1),
        .rs2_addr(rs2),
        .rd_addr(rd),
        .rd_data(alu_out),
        .rs1_data(rs1_data),
        .rs2_data(rs2_data)
    );

    wire [31:0] alu_out;
    wire [31:0] alu_b = (opcode == 7'b0010011) ? imm : rs2_data;
    /* verilator lint_off UNUSEDSIGNAL */
    wire alu_zero;
    /* verilator lint_on UNUSEDSIGNAL */
    alu my_alu (
        .a(rs1_data),
        .b(alu_b),
        .alu_op(4'b0000),
        .result(alu_out),
        .zero(alu_zero)
    );

    assign debug_pc = pc;
    assign debug_instr = instr;
    assign debug_alu_out = alu_out;

endmodule

waves/top.vcd
$version Generated by VerilatedVcd $end
$timescale 1ps $end
 $scope module TOP $end
  $var wire 1 E clk $end
  $var wire 1 F rst_n $end
  $var wire 32 G debug_pc [31:0] $end
  $var wire 32 H debug_instr [31:0] $end
  $var wire 32 I debug_alu_out [31:0] $end
  $scope module top $end
   $var wire 1 E clk $end
   $var wire 1 F rst_n $end
   $var wire 32 G debug_pc [31:0] $end
   $var wire 32 H debug_instr [31:0] $end
   $var wire 32 I debug_alu_out [31:0] $end
   $var wire 32 J pc [31:0] $end
   $var wire 32 H instr [31:0] $end
   $var wire 7 K opcode [6:0] $end
   $var wire 5 L rd [4:0] $end
   $var wire 5 M rs1 [4:0] $end
   $var wire 5 N rs2 [4:0] $end
   $var wire 32 O imm [31:0] $end
   $var wire 32 P rs1_data [31:0] $end
   $var wire 32 Q rs2_data [31:0] $end
   $var wire 1 R reg_we $end
   $var wire 32 S alu_out [31:0] $end
   $var wire 32 T alu_b [31:0] $end
   $var wire 1 U alu_zero $end
   $scope module inst_mem $end
    $var wire 1 E clk $end
    $var wire 1 V we $end
    $var wire 32 J addr [31:0] $end
    $var wire 32 W write_data [31:0] $end
    $var wire 32 H read_data [31:0] $end
    $var wire 32 # i [31:0] $end
   $upscope $end
   $scope module my_alu $end
    $var wire 32 P a [31:0] $end
    $var wire 32 T b [31:0] $end
    $var wire 4 X alu_op [3:0] $end
    $var wire 32 S result [31:0] $end
    $var wire 1 U zero $end
   $upscope $end
   $scope module rf $end
    $var wire 1 E clk $end
    $var wire 1 R we $end
    $var wire 5 M rs1_addr [4:0] $end
    $var wire 5 N rs2_addr [4:0] $end
    $var wire 5 L rd_addr [4:0] $end
    $var wire 32 S rd_data [31:0] $end
    $var wire 32 P rs1_data [31:0] $end
    $var wire 32 Q rs2_data [31:0] $end
    $var wire 32 % regs[0] [31:0] $end
    $var wire 32 & regs[1] [31:0] $end
    $var wire 32 ' regs[2] [31:0] $end
    $var wire 32 ( regs[3] [31:0] $end
    $var wire 32 ) regs[4] [31:0] $end
    $var wire 32 * regs[5] [31:0] $end
    $var wire 32 + regs[6] [31:0] $end
    $var wire 32 , regs[7] [31:0] $end
    $var wire 32 - regs[8] [31:0] $end
    $var wire 32 . regs[9] [31:0] $end
    $var wire 32 / regs[10] [31:0] $end
    $var wire 32 0 regs[11] [31:0] $end
    $var wire 32 1 regs[12] [31:0] $end
    $var wire 32 2 regs[13] [31:0] $end
    $var wire 32 3 regs[14] [31:0] $end
    $var wire 32 4 regs[15] [31:0] $end
    $var wire 32 5 regs[16] [31:0] $end
    $var wire 32 6 regs[17] [31:0] $end
    $var wire 32 7 regs[18] [31:0] $end
    $var wire 32 8 regs[19] [31:0] $end
    $var wire 32 9 regs[20] [31:0] $end
    $var wire 32 : regs[21] [31:0] $end
    $var wire 32 ; regs[22] [31:0] $end
    $var wire 32 < regs[23] [31:0] $end
    $var wire 32 = regs[24] [31:0] $end
    $var wire 32 > regs[25] [31:0] $end
    $var wire 32 ? regs[26] [31:0] $end
    $var wire 32 @ regs[27] [31:0] $end
    $var wire 32 A regs[28] [31:0] $end
    $var wire 32 B regs[29] [31:0] $end
    $var wire 32 C regs[30] [31:0] $end
    $var wire 32 D regs[31] [31:0] $end
    $var wire 32 $ i [31:0] $end
   $upscope $end
  $upscope $end
 $upscope $end
$enddefinitions $end


#0
b00000000000000000000010000000000 #
b00000000000000000000000000100000 $
b00000000000000000000000000000000 %
b00000000000000000000000000000000 &
b00000000000000000000000000000000 '
b00000000000000000000000000000000 (
b00000000000000000000000000000000 )
b00000000000000000000000000000000 *
b00000000000000000000000000000000 +
b00000000000000000000000000000000 ,
b00000000000000000000000000000000 -
b00000000000000000000000000000000 .
b00000000000000000000000000000000 /
b00000000000000000000000000000000 0
b00000000000000000000000000000000 1
b00000000000000000000000000000000 2
b00000000000000000000000000000000 3
b00000000000000000000000000000000 4
b00000000000000000000000000000000 5
b00000000000000000000000000000000 6
b00000000000000000000000000000000 7
b00000000000000000000000000000000 8
b00000000000000000000000000000000 9
b00000000000000000000000000000000 :
b00000000000000000000000000000000 ;
b00000000000000000000000000000000 <
b00000000000000000000000000000000 =
b00000000000000000000000000000000 >
b00000000000000000000000000000000 ?
b00000000000000000000000000000000 @
b00000000000000000000000000000000 A
b00000000000000000000000000000000 B
b00000000000000000000000000000000 C
b00000000000000000000000000000000 D
0E
0F
b00000000000000000000000000000000 G
b00000000101000000000000010010011 H
b00000000000000000000000000001010 I
b00000000000000000000000000000000 J
b0010011 K
b00001 L
b00000 M
b01010 N
b00000000000000000000000000001010 O
b00000000000000000000000000000000 P
b00000000000000000000000000000000 Q
1R
b00000000000000000000000000001010 S
b00000000000000000000000000001010 T
0U
0V
b00000000000000000000000000000000 W
b0000 X
#1
b00000000000000000000000000001010 &
1E
#2
0E
#3
1E
#4
0E
1F
#5
1E
b00000000000000000000000000000100 G
b00000000010100001000000100010011 H
b00000000000000000000000000001111 I
b00000000000000000000000000000100 J
b00010 L
b00001 M
b00101 N
b00000000000000000000000000000101 O
b00000000000000000000000000001010 P
b00000000000000000000000000001111 S
b00000000000000000000000000000101 T
#6
0E
#7
b00000000000000000000000000001111 '
1E
b00000000000000000000000000001000 G
b00000000000000000000000000000000 H
b00000000000000000000000000000000 I
b00000000000000000000000000001000 J
b0000000 K
b00000 L
b00000 M
b00000 N
b00000000000000000000000000000000 O
b00000000000000000000000000000000 P
0R
b00000000000000000000000000000000 S
b00000000000000000000000000000000 T
1U
#8
0E
#9
1E
b00000000000000000000000000001100 G
b00000000000000000000000000001100 J
#10
0E
#11
1E
b00000000000000000000000000010000 G
b00000000000000000000000000010000 J
#12
0E
#13
1E
b00000000000000000000000000010100 G
b00000000000000000000000000010100 J
#14
0E
#15
1E
b00000000000000000000000000011000 G
b00000000000000000000000000011000 J
#16
0E
#17
1E
b00000000000000000000000000011100 G
b00000000000000000000000000011100 J
#18
0E
#19
1E
b00000000000000000000000000100000 G
b00000000000000000000000000100000 J
#20
0E
#21
1E
b00000000000000000000000000100100 G
b00000000000000000000000000100100 J
#22
0E
#23
1E
b00000000000000000000000000101000 G
b00000000000000000000000000101000 J
