hardware/include/defines.v
`define ALU_ADD 4'b0000
`define ALU_SUB 4`b1000
`define ALU_SLL 4'b0001
`define ALU_SLT 4'b0010
`define ALU_SLTU 4'b0011
`define ALU_XOR 4'b1000
`define ALU_SRL 4'b0101
`define ALU_SRA 4'b1101
`define ALU_OR   4'b0110
`define ALU_AND  4'b0111

hardware/src/alu.v
`include "defines.v"

module alu (
    input wire [31:0] a,
    input wire [31:0] b,
    input wire [3:0] alu_op,
    output reg [31:0] result,
    output wire zero
);

    assign zero = (result == 32'b0);

    always @(*) begin
        case (alu_op)
            `ALU_ADD: result = a + b;
            `ALU_SUB: result = a - b;
            `ALU_AND: result = a & b;
            `ALU_OR: result = a | b;
            `ALU_XOR: result = a ^ b;
            `ALU_SLL: result = a << b[4:0];
            `ALU_SRL: result = a >> b[4:0];
            `ALU_SRA: result = $signed(a) >>> b [4:0] ;
            `ALU_SLT: result = ($signed(a) < $signed(b)) ? 32'b1 : 32'b0;
            `ALU_SLTU: result = (a < b) ? 32'b1 : 32'b0;
            default: result = 32'b0;
        endcase
    end
    
endmodule

hardware/src/regfile.v
module regfile (
    input wire clk,
    input wire we,
    input wire [4:0] rs1_addr,
    input wire [4:0] rs2_addr,
    input wire [4:0] rd_addr,
    input wire [31:0] rd_data,
    output wire [31:0] rs1_data,
    output wire [31:0] rs2_data
);
    reg [31:0] regs [31:0];

    assign rs1_data = (rs1_addr == 5'b0) ? 32'b0 : regs[rs1_addr];
    assign rs2_data = (rs2_addr == 5'b0) ? 32'b0 : regs[rs2_addr];

    integer i;
    initial begin
        for (i = 0; i < 32; i = i + 1) regs[i] = 32'b0;
    end

    always @(posedge clk) begin
        if (we && (rd_addr != 5'b0)) begin
            regs[rd_addr] <= rd_data;
        end
    end

endmodule

hardware/src/memory.v
module memory (
    input wire clk,
    input wire we,
    /* verilator lint_off UNUSEDSIGNAL */
    input wire [31:0] addr,
    /* verilator lint_off UNUSEDSIGNAL */
    input wire [31:0] write_data,
    output wire [31:0] read_data
);
    reg [31:0] ram [1023:0];

    assign read_data = ram[addr[11:2]];

    always @(posedge clk) begin
        if (we) begin
            ram[addr[11:2]] <= write_data;
        end

    end

    integer i;
    initial begin
        for (i = 0; i < 1024; i = i + 1) begin
            ram[i] = 32'b0;
        end
    end
    
endmodule

hardware/src/top.v
`include "defines"
module top (
    input wire clk,
    input wire rst_n,
    output wire [31:0] debug_pc,
    output wire [31:0] debug_instr,
    output wire [31:0] debug_alu_out
);
    reg [31:0] pc;

    /* verilator lint_off UNUSEDSIGNAL */
    wire [31:0] instr;
    /* verilator lint_on UNUSEDSIGNAL */

    memory inst_mem (
        .clk(clk),
        .we(1'b0),
        .addr(pc),
        .write_data(32'b0),
        .read_data(instr)
    );

    wire [6:0] opcode = instr[6:0];
    wire [4:0] rd = instr[11:7];
    wire [4:0] rs1 = instr[19:15];
    wire [4:0] rs2 = instr[24:20];

    wire [31:0] rs1_data, rs2_data;

    wire [31:0] imm_i = {{20{instr[31]}}, instr[31:20]};
    wire [31:0] imm_s = {{20{instr[31]}}, instr[31:25], instr[11:7]};
    wire [31:0] imm_b = {{20{instr[31]}}, instr[7], instr[30:25], instr[11:8], 1'b0};
    wire [31:0] imm = (opcode == 7'b0100011) ? imm_s : imm_i;
    
    wire is_beq = (opcode == 7'b1100011);
    wire take_branch = is_beq && alu_zero;

    wire [31:0] pc_next;
    wire [31:0] pc_plus4 = pc + 4;
    wire [31:0] pc_target = pc + imm_b;

    assign pc_next = take_branch ? pc_target : pc_plus4;

    always @(posedge clk or negedge rst_n) begin
        if (!rst_n) begin
            pc <= 32'b0;
        end
        else begin
            pc <= pc_next;
        end
    end

    wire is_lw = (opcode == 7'b0000011);
    wire is_sw = (opcode == 7'b0100011);
    wire reg_we = (opcode == 7'b0010011 || opcode == 7'b0110011 || is_lw);

    wire [31:0] mem_read_data;

    memory data_mem (
        .clk(clk),
        .we(is_sw),
        .addr(alu_out),
        .write_data(rs2_data),
        .read_data(mem_read_data)
    );

    wire [31:0] rf_wd = is_lw ? mem_read_data : alu_out;

    regfile rf (
        .clk(clk),
        .we(reg_we),
        .rs1_addr(rs1),
        .rs2_addr(rs2),
        .rd_addr(rd),
        .rd_data(rf_wd),
        .rs1_data(rs1_data),
        .rs2_data(rs2_data)
    );

    wire [31:0] alu_out;
    wire [31:0] alu_b = (opcode == 7'b0010011 || is_lw || is_sw) ? imm : rs2_data;
    /* verilator lint_off UNUSEDSIGNAL */
    wire alu_zero;
    /* verilator lint_on UNUSEDSIGNAL */
    wire [3:0] alu_ctrl = is_beq ? `ALU_SUB : `ALU_ADD;

    alu my_alu (
        .a(rs1_data),
        .b(alu_b),
        .alu_op(alu_ctrl),
        .result(alu_out),
        .zero(alu_zero)
    );

    assign debug_pc = pc;
    assign debug_instr = instr;
    assign debug_alu_out = alu_out;

endmodule

waves/top.vcd
$version Generated by VerilatedVcd $end
$timescale 1ps $end
 $scope module TOP $end
  $var wire 1 K clk $end
  $var wire 1 L rst_n $end
  $var wire 32 M debug_pc [31:0] $end
  $var wire 32 N debug_instr [31:0] $end
  $var wire 32 O debug_alu_out [31:0] $end
  $scope module top $end
   $var wire 1 K clk $end
   $var wire 1 L rst_n $end
   $var wire 32 M debug_pc [31:0] $end
   $var wire 32 N debug_instr [31:0] $end
   $var wire 32 O debug_alu_out [31:0] $end
   $var wire 32 P pc [31:0] $end
   $var wire 32 N instr [31:0] $end
   $var wire 7 Q opcode [6:0] $end
   $var wire 5 R rd [4:0] $end
   $var wire 5 S rs1 [4:0] $end
   $var wire 5 T rs2 [4:0] $end
   $var wire 32 F rs1_data [31:0] $end
   $var wire 32 G rs2_data [31:0] $end
   $var wire 32 U imm_i [31:0] $end
   $var wire 32 V imm_s [31:0] $end
   $var wire 32 W imm_b [31:0] $end
   $var wire 32 X imm [31:0] $end
   $var wire 1 Y is_beq $end
   $var wire 1 Z take_branch $end
   $var wire 32 [ pc_next [31:0] $end
   $var wire 32 \ pc_plus4 [31:0] $end
   $var wire 32 ] pc_target [31:0] $end
   $var wire 1 ^ is_lw $end
   $var wire 1 _ is_sw $end
   $var wire 1 ` reg_we $end
   $var wire 32 a mem_read_data [31:0] $end
   $var wire 32 b rf_wd [31:0] $end
   $var wire 32 H alu_out [31:0] $end
   $var wire 32 I alu_b [31:0] $end
   $var wire 1 J alu_zero $end
   $var wire 4 c alu_ctrl [3:0] $end
   $scope module data_mem $end
    $var wire 1 K clk $end
    $var wire 1 _ we $end
    $var wire 32 H addr [31:0] $end
    $var wire 32 G write_data [31:0] $end
    $var wire 32 a read_data [31:0] $end
    $var wire 32 # i [31:0] $end
   $upscope $end
   $scope module inst_mem $end
    $var wire 1 K clk $end
    $var wire 1 d we $end
    $var wire 32 P addr [31:0] $end
    $var wire 32 e write_data [31:0] $end
    $var wire 32 N read_data [31:0] $end
    $var wire 32 $ i [31:0] $end
   $upscope $end
   $scope module my_alu $end
    $var wire 32 F a [31:0] $end
    $var wire 32 I b [31:0] $end
    $var wire 4 c alu_op [3:0] $end
    $var wire 32 H result [31:0] $end
    $var wire 1 J zero $end
   $upscope $end
   $scope module rf $end
    $var wire 1 K clk $end
    $var wire 1 ` we $end
    $var wire 5 S rs1_addr [4:0] $end
    $var wire 5 T rs2_addr [4:0] $end
    $var wire 5 R rd_addr [4:0] $end
    $var wire 32 b rd_data [31:0] $end
    $var wire 32 F rs1_data [31:0] $end
    $var wire 32 G rs2_data [31:0] $end
    $var wire 32 & regs[0] [31:0] $end
    $var wire 32 ' regs[1] [31:0] $end
    $var wire 32 ( regs[2] [31:0] $end
    $var wire 32 ) regs[3] [31:0] $end
    $var wire 32 * regs[4] [31:0] $end
    $var wire 32 + regs[5] [31:0] $end
    $var wire 32 , regs[6] [31:0] $end
    $var wire 32 - regs[7] [31:0] $end
    $var wire 32 . regs[8] [31:0] $end
    $var wire 32 / regs[9] [31:0] $end
    $var wire 32 0 regs[10] [31:0] $end
    $var wire 32 1 regs[11] [31:0] $end
    $var wire 32 2 regs[12] [31:0] $end
    $var wire 32 3 regs[13] [31:0] $end
    $var wire 32 4 regs[14] [31:0] $end
    $var wire 32 5 regs[15] [31:0] $end
    $var wire 32 6 regs[16] [31:0] $end
    $var wire 32 7 regs[17] [31:0] $end
    $var wire 32 8 regs[18] [31:0] $end
    $var wire 32 9 regs[19] [31:0] $end
    $var wire 32 : regs[20] [31:0] $end
    $var wire 32 ; regs[21] [31:0] $end
    $var wire 32 < regs[22] [31:0] $end
    $var wire 32 = regs[23] [31:0] $end
    $var wire 32 > regs[24] [31:0] $end
    $var wire 32 ? regs[25] [31:0] $end
    $var wire 32 @ regs[26] [31:0] $end
    $var wire 32 A regs[27] [31:0] $end
    $var wire 32 B regs[28] [31:0] $end
    $var wire 32 C regs[29] [31:0] $end
    $var wire 32 D regs[30] [31:0] $end
    $var wire 32 E regs[31] [31:0] $end
    $var wire 32 % i [31:0] $end
   $upscope $end
  $upscope $end
 $upscope $end
$enddefinitions $end


#0
b00000000000000000000010000000000 #
b00000000000000000000010000000000 $
b00000000000000000000000000100000 %
b00000000000000000000000000000000 &
b00000000000000000000000000000000 '
b00000000000000000000000000000000 (
b00000000000000000000000000000000 )
b00000000000000000000000000000000 *
b00000000000000000000000000000000 +
b00000000000000000000000000000000 ,
b00000000000000000000000000000000 -
b00000000000000000000000000000000 .
b00000000000000000000000000000000 /
b00000000000000000000000000000000 0
b00000000000000000000000000000000 1
b00000000000000000000000000000000 2
b00000000000000000000000000000000 3
b00000000000000000000000000000000 4
b00000000000000000000000000000000 5
b00000000000000000000000000000000 6
b00000000000000000000000000000000 7
b00000000000000000000000000000000 8
b00000000000000000000000000000000 9
b00000000000000000000000000000000 :
b00000000000000000000000000000000 ;
b00000000000000000000000000000000 <
b00000000000000000000000000000000 =
b00000000000000000000000000000000 >
b00000000000000000000000000000000 ?
b00000000000000000000000000000000 @
b00000000000000000000000000000000 A
b00000000000000000000000000000000 B
b00000000000000000000000000000000 C
b00000000000000000000000000000000 D
b00000000000000000000000000000000 E
b00000000000000000000000000000000 F
b00000000000000000000000000000000 G
b00000000000000000000000000000101 H
b00000000000000000000000000000101 I
0J
0K
0L
b00000000000000000000000000000000 M
b00000000010100000000000010010011 N
b00000000000000000000000000000101 O
b00000000000000000000000000000000 P
b0010011 Q
b00001 R
b00000 S
b00101 T
b00000000000000000000000000000101 U
b00000000000000000000000000000001 V
b00000000000000000000100000000000 W
b00000000000000000000000000000101 X
0Y
0Z
b00000000000000000000000000000100 [
b00000000000000000000000000000100 \
b00000000000000000000100000000000 ]
0^
0_
1`
b00000000010100000000000100010011 a
b00000000000000000000000000000101 b
b0000 c
0d
b00000000000000000000000000000000 e
#1
b00000000000000000000000000000101 '
1K
#2
0K
#3
1K
#4
0K
1L
#5
1K
b00000000000000000000000000000100 M
b00000000010100000000000100010011 N
b00000000000000000000000000000100 P
b00010 R
b00000000000000000000000000000010 V
b00000000000000000000000000000010 W
b00000000000000000000000000001000 [
b00000000000000000000000000001000 \
b00000000000000000000000000000110 ]
#6
0K
#7
b00000000000000000000000000000101 (
b00000000000000000000000000000101 F
b00000000000000000000000000000101 G
b00000000000000000000000000000000 H
1J
1K
b00000000000000000000000000001000 M
b00000000001000001000010001100011 N
b00000000000000000000000000000000 O
b00000000000000000000000000001000 P
b1100011 Q
b01000 R
b00001 S
b00010 T
b00000000000000000000000000000010 U
b00000000000000000000000000001000 V
b00000000000000000000000000001000 W
b00000000000000000000000000000010 X
1Y
1Z
b00000000000000000000000000010000 [
b00000000000000000000000000001100 \
b00000000000000000000000000010000 ]
0`
b00000000010100000000000010010011 a
b00000000000000000000000000000000 b
b1000 c
#8
0K
#9
b00000000000000000000000000000000 F
b00000000000000000000000000000001 H
b00000000000000000000000000000001 I
0J
1K
b00000000000000000000000000010000 M
b00000000000100000000001000010011 N
b00000000000000000000000000000001 O
b00000000000000000000000000010000 P
b0010011 Q
b00100 R
b00000 S
b00001 T
b00000000000000000000000000000001 U
b00000000000000000000000000000100 V
b00000000000000000000000000000100 W
b00000000000000000000000000000001 X
0Y
0Z
b00000000000000000000000000010100 [
b00000000000000000000000000010100 \
b00000000000000000000000000010100 ]
1`
b00000000000000000000000000000001 b
b0000 c
#10
0K
#11
b00000000000000000000000000000001 *
b00000000000000000000000000000000 G
b00000000000000000000000000000000 H
b00000000000000000000000000000000 I
1J
1K
b00000000000000000000000000010100 M
b00000000000000000000000000000000 N
b00000000000000000000000000000000 O
b00000000000000000000000000010100 P
b0000000 Q
b00000 R
b00000 T
b00000000000000000000000000000000 U
b00000000000000000000000000000000 V
b00000000000000000000000000000000 W
b00000000000000000000000000000000 X
b00000000000000000000000000011000 [
b00000000000000000000000000011000 \
0`
b00000000000000000000000000000000 b
#12
0K
#13
1K
b00000000000000000000000000011000 M
b00000000000000000000000000011000 P
b00000000000000000000000000011100 [
b00000000000000000000000000011100 \
b00000000000000000000000000011000 ]
#14
0K
#15
1K
b00000000000000000000000000011100 M
b00000000000000000000000000011100 P
b00000000000000000000000000100000 [
b00000000000000000000000000100000 \
b00000000000000000000000000011100 ]
#16
0K
#17
1K
b00000000000000000000000000100000 M
b00000000000000000000000000100000 P
b00000000000000000000000000100100 [
b00000000000000000000000000100100 \
b00000000000000000000000000100000 ]
#18
0K
#19
1K
b00000000000000000000000000100100 M
b00000000000000000000000000100100 P
b00000000000000000000000000101000 [
b00000000000000000000000000101000 \
b00000000000000000000000000100100 ]
#20
0K
#21
1K
b00000000000000000000000000101000 M
b00000000000000000000000000101000 P
b00000000000000000000000000101100 [
b00000000000000000000000000101100 \
b00000000000000000000000000101000 ]
#22
0K
#23
1K
b00000000000000000000000000101100 M
b00000000000000000000000000101100 P
b00000000000000000000000000110000 [
b00000000000000000000000000110000 \
b00000000000000000000000000101100 ]
