hardware/include/defines.v
`define ALU_ADD 4'b0000
`define ALU_SUB 4`b1000
`define ALU_SLL 4'b0001
`define ALU_SLT 4'b0010
`define ALU_SLTU 4'b0011
`define ALU_XOR 4'b1000
`define ALU_SRL 4'b0101
`define ALU_SRA 4'b1101
`define ALU_OR   4'b0110
`define ALU_AND  4'b0111

hardware/src/alu.v
`include "defines.v"

module alu (
    input wire [31:0] a,
    input wire [31:0] b,
    input wire [3:0] alu_op,
    output reg [31:0] result,
    output wire zero
);

    assign zero = (result == 32'b0);

    always @(*) begin
        case (alu_op)
            `ALU_ADD: result = a + b;
            `ALU_SUB: result = a - b;
            `ALU_AND: result = a & b;
            `ALU_OR: result = a | b;
            `ALU_XOR: result = a ^ b;
            `ALU_SLL: result = a << b[4:0];
            `ALU_SRL: result = a >> b[4:0];
            `ALU_SRA: result = $signed(a) >>> b [4:0] ;
            `ALU_SLT: result = ($signed(a) < $signed(b)) ? 32'b1 : 32'b0;
            `ALU_SLTU: result = (a < b) ? 32'b1 : 32'b0;
            default: result = 32'b0;
        endcase
    end
    
endmodule

hardware/src/regfile.v
module regfile (
    input wire clk,
    input wire we,
    input wire [4:0] rs1_addr,
    input wire [4:0] rs2_addr,
    input wire [4:0] rd_addr,
    input wire [31:0] rd_data,
    output wire [31:0] rs1_data,
    output wire [31:0] rs2_data
);
    reg [31:0] regs [31:0];

    assign rs1_data = (rs1_addr == 5'b0) ? 32'b0 : regs[rs1_addr];
    assign rs2_data = (rs2_addr == 5'b0) ? 32'b0 : regs[rs2_addr];

    integer i;
    initial begin
        for (i = 0; i < 32; i = i + 1) regs[i] = 32'b0;
    end

    always @(posedge clk) begin
        if (we && (rd_addr != 5'b0)) begin
            regs[rd_addr] <= rd_data;
        end
    end

endmodule

hardware/src/memory.v
module memory (
    input wire clk,
    input wire we,
    /* verilator lint_off UNUSEDSIGNAL */
    input wire [31:0] addr,
    /* verilator lint_off UNUSEDSIGNAL */
    input wire [31:0] write_data,
    output wire [31:0] read_data
);
    reg [31:0] ram [1023:0];

    assign read_data = ram[addr[11:2]];

    always @(posedge clk) begin
        if (we) begin
            ram[addr[11:2]] <= write_data;
        end

    end

    integer i;
    initial begin
        for (i = 0; i < 1024; i = i + 1) begin
            ram[i] = 32'b0;
        end
    end
    
endmodule

hardware/src/top.v
`include "defines.v"
module top (
    input wire clk,
    input wire rst_n,
    output wire [31:0] debug_pc,
    output wire [31:0] debug_instr,
    output wire [31:0] debug_alu_out
);
    reg [31:0] pc;

    /* verilator lint_off UNUSEDSIGNAL */
    wire [31:0] instr;
    /* verilator lint_on UNUSEDSIGNAL */

    memory inst_mem (
        .clk(clk),
        .we(1'b0),
        .addr(pc),
        .write_data(32'b0),
        .read_data(instr)
    );

    wire [6:0] opcode = instr[6:0];
    wire [4:0] rd     = instr[11:7];
    wire [4:0] rs1    = instr[19:15];
    wire [4:0] rs2    = instr[24:20];
    wire [2:0] funct3 = instr[14:12];
    /* verilator lint_off UNUSEDSIGNAL */
    wire [6:0] funct7 = instr[31:25];
    /* verilator lint_on UNUSEDSIGNAL */

    wire [31:0] rs1_data, rs2_data;

    localparam OP_I_ALU  = 7'b0010011;
    localparam OP_I_LOAD = 7'b0000011;
    localparam OP_S_TYPE = 7'b0100011;
    localparam OP_B_TYPE = 7'b1100011;
    localparam OP_R_TYPE = 7'b0110011;
    localparam OP_LUI    = 7'b0110111;
    localparam OP_AUIPC  = 7'b0010111;
    localparam OP_JAL    = 7'b1101111;
    localparam OP_JALR = 7'b1100111;

    wire [31:0] imm_i = {{20{instr[31]}}, instr[31:20]};
    wire [31:0] imm_s = {{20{instr[31]}}, instr[31:25], instr[11:7]};
    wire [31:0] imm_b = {{20{instr[31]}}, instr[7], instr[30:25], instr[11:8], 1'b0};
    wire [31:0] imm_u = {instr[31:12], 12'b0};
    wire [31:0] imm_j = {{12{instr[31]}}, instr[19:12], instr[20], instr[30:21], 1'b0};

    reg [31:0] imm;
    always @(*) begin
        case (opcode)
            OP_I_ALU, OP_I_LOAD, OP_JALR: imm = imm_i;
            OP_S_TYPE:           imm = imm_s;
            OP_B_TYPE:           imm = imm_b;
            OP_LUI, OP_AUIPC:    imm = imm_u;
            OP_JAL:              imm = imm_j;
            default: imm = 32'b0;
        endcase
    end
    
    wire is_jal = (opcode == OP_JAL);
    wire is_beq = (opcode == OP_B_TYPE);
    wire is_jalr = (opcode == OP_JALR);

    reg branch_condition;
    always @(*) begin
        case (funct3)
            3'b000: branch_condition = alu_zero;
            3'b001: branch_condition = !alu_zero;
            3'b100: branch_condition = alu_out[0];
            3'b101: branch_condition = !alu_out[0];
            3'b110: branch_condition = alu_out[0];
            3'b111: branch_condition = !alu_out[0];
            default: branch_condition = 1'b0;
        endcase
    end

    wire take_branch = (is_beq && branch_condition) || is_jal || is_jalr;

    wire [31:0] jump_base   = is_jalr ? rs1_data : pc;
    wire [31:0] jump_offset = is_jal  ? imm_j    : is_jalr ? imm_i : imm_b;

    wire [31:0] pc_next;
    wire [31:0] pc_target_raw = $unsigned($signed(jump_base) + $signed(jump_offset));
    wire [31:0] pc_target     = is_jalr ? (pc_target_raw & 32'hfffffffe) : pc_target_raw;
    wire [31:0] pc_plus4 = pc + 4;

    assign pc_next = take_branch ? pc_target : pc_plus4;

    always @(posedge clk or negedge rst_n) begin
        if (!rst_n) begin
            pc <= 32'b0;
        end
        else begin
            pc <= pc_next;
        end
    end

    wire is_lw = (opcode == OP_I_LOAD);
    wire is_sw = (opcode == OP_S_TYPE);
    wire reg_we = (opcode == OP_I_ALU || opcode == OP_R_TYPE || is_lw || 
               opcode == OP_LUI || opcode == OP_AUIPC || is_jal || is_jalr);

    wire [31:0] mem_read_data;

    memory data_mem (
        .clk(clk),
        .we(is_sw),
        .addr(alu_out),
        .write_data(rs2_data),
        .read_data(mem_read_data)
    );

    /* verilator lint_off UNOPTFLAT */
    wire [31:0] rf_wd = is_lw ? mem_read_data : (is_jal || is_jalr) ? pc_plus4 : alu_out;
    /* verilator lint_on UNOPTFLAT */

    regfile rf (
        .clk(clk),
        .we(reg_we),
        .rs1_addr(rs1),
        .rs2_addr(rs2),
        .rd_addr(rd),
        .rd_data(rf_wd),
        .rs1_data(rs1_data),
        .rs2_data(rs2_data)
    );

    reg [3:0] alu_ctrl; 
    always @(*) begin
        case (opcode)
            OP_R_TYPE: begin
                case (funct3)
                    3'b000: alu_ctrl = funct7[5] ? `ALU_SUB : `ALU_ADD;
                    3'b101: alu_ctrl = funct7[5] ? `ALU_SRA : `ALU_SRL;
                    default: alu_ctrl = {1'b0, funct3};
                endcase
            end

            OP_I_ALU:begin
                if (funct3 == 3'b101 && funct7[5]) begin
                    alu_ctrl = `ALU_SRA;
                end
                else if (funct3 == 3'b001)
                    alu_ctrl = `ALU_SLL;
                else if (funct3 == 3'b101)
                    alu_ctrl = `ALU_SRL;
                else begin
                    alu_ctrl = {1'b0, funct3};
                end
            end

            OP_B_TYPE: begin
                case (funct3)
                    3'b000, 3'b001: alu_ctrl = `ALU_SUB;
                    3'b100, 3'b101: alu_ctrl = `ALU_SLT;
                    3'b110, 3'b111: alu_ctrl = `ALU_SLTU;
                    default: alu_ctrl = `ALU_SUB;
                endcase
            end

            OP_JALR: alu_ctrl = `ALU_ADD;
            default: alu_ctrl = `ALU_ADD;
        endcase
    end

    wire [31:0] alu_out;
    wire use_imm = (opcode == OP_I_ALU || opcode == OP_I_LOAD || opcode == OP_S_TYPE || opcode == OP_LUI || opcode == OP_AUIPC);
    wire [31:0] alu_a = (opcode == OP_AUIPC) ? pc : (opcode == OP_LUI)   ? 32'b0 : rs1_data;
    wire [31:0] alu_b = use_imm ? imm : rs2_data;

    /* verilator lint_off UNUSEDSIGNAL */
    wire alu_zero;
    /* verilator lint_on UNUSEDSIGNAL */

    alu my_alu (
        .a(alu_a),
        .b(alu_b),
        .alu_op(alu_ctrl),
        .result(alu_out),
        .zero(alu_zero)
    );

    assign debug_pc = pc;
    assign debug_instr = instr;
    assign debug_alu_out = alu_out;

endmodule

waves/top.vcd
$version Generated by VerilatedVcd $end
$timescale 1ps $end
 $scope module TOP $end
  $var wire 1 T clk $end
  $var wire 1 U rst_n $end
  $var wire 32 V debug_pc [31:0] $end
  $var wire 32 W debug_instr [31:0] $end
  $var wire 32 X debug_alu_out [31:0] $end
  $scope module top $end
   $var wire 1 T clk $end
   $var wire 1 U rst_n $end
   $var wire 32 V debug_pc [31:0] $end
   $var wire 32 W debug_instr [31:0] $end
   $var wire 32 X debug_alu_out [31:0] $end
   $var wire 32 F pc [31:0] $end
   $var wire 32 W instr [31:0] $end
   $var wire 7 Y opcode [6:0] $end
   $var wire 5 Z rd [4:0] $end
   $var wire 5 [ rs1 [4:0] $end
   $var wire 5 \ rs2 [4:0] $end
   $var wire 3 ] funct3 [2:0] $end
   $var wire 7 ^ funct7 [6:0] $end
   $var wire 32 M rs1_data [31:0] $end
   $var wire 32 N rs2_data [31:0] $end
   $var wire 7 p OP_I_ALU [6:0] $end
   $var wire 7 q OP_I_LOAD [6:0] $end
   $var wire 7 r OP_S_TYPE [6:0] $end
   $var wire 7 s OP_B_TYPE [6:0] $end
   $var wire 7 t OP_R_TYPE [6:0] $end
   $var wire 7 u OP_LUI [6:0] $end
   $var wire 7 v OP_AUIPC [6:0] $end
   $var wire 7 w OP_JAL [6:0] $end
   $var wire 7 x OP_JALR [6:0] $end
   $var wire 32 G imm_i [31:0] $end
   $var wire 32 _ imm_s [31:0] $end
   $var wire 32 H imm_b [31:0] $end
   $var wire 32 ` imm_u [31:0] $end
   $var wire 32 I imm_j [31:0] $end
   $var wire 32 J imm [31:0] $end
   $var wire 1 a is_jal $end
   $var wire 1 b is_beq $end
   $var wire 1 c is_jalr $end
   $var wire 1 d branch_condition $end
   $var wire 1 e take_branch $end
   $var wire 32 f jump_base [31:0] $end
   $var wire 32 g jump_offset [31:0] $end
   $var wire 32 h pc_next [31:0] $end
   $var wire 32 O pc_target_raw [31:0] $end
   $var wire 32 i pc_target [31:0] $end
   $var wire 32 K pc_plus4 [31:0] $end
   $var wire 1 j is_lw $end
   $var wire 1 k is_sw $end
   $var wire 1 l reg_we $end
   $var wire 32 m mem_read_data [31:0] $end
   $var wire 32 n rf_wd [31:0] $end
   $var wire 4 L alu_ctrl [3:0] $end
   $var wire 32 P alu_out [31:0] $end
   $var wire 1 o use_imm $end
   $var wire 32 Q alu_a [31:0] $end
   $var wire 32 R alu_b [31:0] $end
   $var wire 1 S alu_zero $end
   $scope module data_mem $end
    $var wire 1 T clk $end
    $var wire 1 k we $end
    $var wire 32 P addr [31:0] $end
    $var wire 32 N write_data [31:0] $end
    $var wire 32 m read_data [31:0] $end
    $var wire 32 # i [31:0] $end
   $upscope $end
   $scope module inst_mem $end
    $var wire 1 T clk $end
    $var wire 1 y we $end
    $var wire 32 F addr [31:0] $end
    $var wire 32 z write_data [31:0] $end
    $var wire 32 W read_data [31:0] $end
    $var wire 32 $ i [31:0] $end
   $upscope $end
   $scope module my_alu $end
    $var wire 32 Q a [31:0] $end
    $var wire 32 R b [31:0] $end
    $var wire 4 L alu_op [3:0] $end
    $var wire 32 P result [31:0] $end
    $var wire 1 S zero $end
   $upscope $end
   $scope module rf $end
    $var wire 1 T clk $end
    $var wire 1 l we $end
    $var wire 5 [ rs1_addr [4:0] $end
    $var wire 5 \ rs2_addr [4:0] $end
    $var wire 5 Z rd_addr [4:0] $end
    $var wire 32 n rd_data [31:0] $end
    $var wire 32 M rs1_data [31:0] $end
    $var wire 32 N rs2_data [31:0] $end
    $var wire 32 & regs[0] [31:0] $end
    $var wire 32 ' regs[1] [31:0] $end
    $var wire 32 ( regs[2] [31:0] $end
    $var wire 32 ) regs[3] [31:0] $end
    $var wire 32 * regs[4] [31:0] $end
    $var wire 32 + regs[5] [31:0] $end
    $var wire 32 , regs[6] [31:0] $end
    $var wire 32 - regs[7] [31:0] $end
    $var wire 32 . regs[8] [31:0] $end
    $var wire 32 / regs[9] [31:0] $end
    $var wire 32 0 regs[10] [31:0] $end
    $var wire 32 1 regs[11] [31:0] $end
    $var wire 32 2 regs[12] [31:0] $end
    $var wire 32 3 regs[13] [31:0] $end
    $var wire 32 4 regs[14] [31:0] $end
    $var wire 32 5 regs[15] [31:0] $end
    $var wire 32 6 regs[16] [31:0] $end
    $var wire 32 7 regs[17] [31:0] $end
    $var wire 32 8 regs[18] [31:0] $end
    $var wire 32 9 regs[19] [31:0] $end
    $var wire 32 : regs[20] [31:0] $end
    $var wire 32 ; regs[21] [31:0] $end
    $var wire 32 < regs[22] [31:0] $end
    $var wire 32 = regs[23] [31:0] $end
    $var wire 32 > regs[24] [31:0] $end
    $var wire 32 ? regs[25] [31:0] $end
    $var wire 32 @ regs[26] [31:0] $end
    $var wire 32 A regs[27] [31:0] $end
    $var wire 32 B regs[28] [31:0] $end
    $var wire 32 C regs[29] [31:0] $end
    $var wire 32 D regs[30] [31:0] $end
    $var wire 32 E regs[31] [31:0] $end
    $var wire 32 % i [31:0] $end
   $upscope $end
  $upscope $end
 $upscope $end
$enddefinitions $end


#0
b00000000000000000000010000000000 #
b00000000000000000000010000000000 $
b00000000000000000000000000100000 %
b00000000000000000000000000000000 &
b00000000000000000000000000000000 '
b00000000000000000000000000000000 (
b00000000000000000000000000000000 )
b00000000000000000000000000000000 *
b00000000000000000000000000000000 +
b00000000000000000000000000000000 ,
b00000000000000000000000000000000 -
b00000000000000000000000000000000 .
b00000000000000000000000000000000 /
b00000000000000000000000000000000 0
b00000000000000000000000000000000 1
b00000000000000000000000000000000 2
b00000000000000000000000000000000 3
b00000000000000000000000000000000 4
b00000000000000000000000000000000 5
b00000000000000000000000000000000 6
b00000000000000000000000000000000 7
b00000000000000000000000000000000 8
b00000000000000000000000000000000 9
b00000000000000000000000000000000 :
b00000000000000000000000000000000 ;
b00000000000000000000000000000000 <
b00000000000000000000000000000000 =
b00000000000000000000000000000000 >
b00000000000000000000000000000000 ?
b00000000000000000000000000000000 @
b00000000000000000000000000000000 A
b00000000000000000000000000000000 B
b00000000000000000000000000000000 C
b00000000000000000000000000000000 D
b00000000000000000000000000000000 E
b00000000000000000000000000000000 F
b00000000000000000000000000000101 G
b00000000000000000000100000000000 H
b00000000000000000000100000000100 I
b00000000000000000000000000000101 J
b00000000000000000000000000000100 K
b0000 L
b00000000000000000000000000000000 M
b00000000000000000000000000000000 N
b00000000000000000000100000000000 O
b00000000000000000000000000000101 P
b00000000000000000000000000000000 Q
b00000000000000000000000000000101 R
0S
0T
0U
b00000000000000000000000000000000 V
b00000000010100000000000010010011 W
b00000000000000000000000000000101 X
b0010011 Y
b00001 Z
b00000 [
b00101 \
b000 ]
b0000000 ^
b00000000000000000000000000000001 _
b00000000010100000000000000000000 `
0a
0b
0c
0d
0e
b00000000000000000000000000000000 f
b00000000000000000000100000000000 g
b00000000000000000000000000000100 h
b00000000000000000000100000000000 i
0j
0k
1l
b00000000101000000000000100010011 m
b00000000000000000000000000000101 n
1o
b0010011 p
b0000011 q
b0100011 r
b1100011 s
b0110011 t
b0110111 u
b0010111 v
b1101111 w
b1100111 x
0y
b00000000000000000000000000000000 z
#1
b00000000000000000000000000000101 '
1T
#2
0T
#3
1T
#4
1U
#5
0T
#6
b00000000000000000000000000000100 F
b00000000000000000000000000001010 G
b00000000000000000000000000000010 H
b00000000000000000000000000001010 I
b00000000000000000000000000001010 J
b00000000000000000000000000001000 K
b00000000000000000000000000000110 O
b00000000000000000000000000001010 P
b00000000000000000000000000001010 R
1T
b00000000000000000000000000000100 V
b00000000101000000000000100010011 W
b00000000000000000000000000001010 X
b00010 Z
b01010 \
b00000000000000000000000000000010 _
b00000000101000000000000000000000 `
b00000000000000000000000000000100 f
b00000000000000000000000000000010 g
b00000000000000000000000000001000 h
b00000000000000000000000000000110 i
b00000000001000001000000110110011 m
b00000000000000000000000000001010 n
#7
0T
#8
b00000000000000000000000000001010 (
b00000000000000000000000000001000 F
b00000000000000000000000000000010 G
b00000000000000000000100000000010 H
b00000000000000001000000000000010 I
b00000000000000000000000000000000 J
b00000000000000000000000000001100 K
b00000000000000000000000000000101 M
b00000000000000000000000000001010 N
b00000000000000000000100000001010 O
b00000000000000000000000000001111 P
b00000000000000000000000000000101 Q
1T
b00000000000000000000000000001000 V
b00000000001000001000000110110011 W
b00000000000000000000000000001111 X
b0110011 Y
b00011 Z
b00001 [
b00010 \
b00000000000000000000000000000011 _
b00000000001000001000000000000000 `
b00000000000000000000000000001000 f
b00000000000000000000100000000010 g
b00000000000000000000000000001100 h
b00000000000000000000100000001010 i
b00000000001000001111001000110011 m
b00000000000000000000000000001111 n
0o
#9
0T
#10
b00000000000000000000000000001111 )
b00000000000000000000000000001100 F
b00000000000000000000000000000100 H
b00000000000000001111000000000010 I
b00000000000000000000000000010000 K
b0111 L
b00000000000000000000000000010000 O
b00000000000000000000000000000000 P
1S
1T
b00000000000000000000000000001100 V
b00000000001000001111001000110011 W
b00000000000000000000000000000000 X
b00100 Z
b111 ]
b00000000000000000000000000000100 _
b00000000001000001111000000000000 `
1d
b00000000000000000000000000001100 f
b00000000000000000000000000000100 g
b00000000000000000000000000010000 h
b00000000000000000000000000010000 i
b00000000010100000000000010010011 m
b00000000000000000000000000000000 n
#11
0T
#12
b00000000000000000000000000010000 F
b00000000000000000000100000000100 H
b00000000000000001110000000000010 I
b00000000000000000000000000010100 K
b0110 L
b00000000000000000000100000010100 O
b00000000000000000000000000001111 P
0S
1T
b00000000000000000000000000010000 V
b00000000001000001110001010110011 W
b00000000000000000000000000001111 X
b00101 Z
b110 ]
b00000000000000000000000000000101 _
b00000000001000001110000000000000 `
b00000000000000000000000000010000 f
b00000000000000000000100000000100 g
b00000000000000000000000000010100 h
b00000000000000000000100000010100 i
b00000000001000001111001000110011 m
b00000000000000000000000000001111 n
#13
0T
#14
b00000000000000000000000000001111 +
b00000000000000000000000000010100 F
b00000000000000000000000000000001 G
b00000000000000000000000000000100 H
b00000000000000000010100000000000 I
b00000000000000000000000000000100 J
b00000000000000000000000000011000 K
b0000 L
b00000000000000000000000000000000 M
b00000000000000000000000000000101 N
b00000000000000000000000000011000 O
b00000000000000000000000000000100 P
b00000000000000000000000000000000 Q
b00000000000000000000000000000100 R
1T
b00000000000000000000000000010100 V
b00000000000100000010001000100011 W
b00000000000000000000000000000100 X
b0100011 Y
b00100 Z
b00000 [
b00001 \
b010 ]
b00000000000000000000000000000100 _
b00000000000100000010000000000000 `
0d
b00000000000000000000000000010100 f
b00000000000000000000000000000100 g
b00000000000000000000000000011000 h
b00000000000000000000000000011000 i
1k
0l
b00000000101000000000000100010011 m
b00000000000000000000000000000100 n
1o
#15
0T
#16
b00000000000000000000000000011000 F
b00000000000000000000000000000100 G
b00000000000000000000000000000110 H
b00000000000000000010000000000100 I
b00000000000000000000000000011100 K
b00000000000000000000000000000000 N
b00000000000000000000000000011110 O
1T
b00000000000000000000000000011000 V
b00000000010000000010001100000011 W
b0000011 Y
b00110 Z
b00100 \
b00000000000000000000000000000110 _
b00000000010000000010000000000000 `
b00000000000000000000000000011000 f
b00000000000000000000000000000110 g
b00000000000000000000000000011100 h
b00000000000000000000000000011110 i
1j
0k
1l
b00000000000000000000000000000101 m
b00000000000000000000000000000101 n
#17
0T
#18
b00000000000000000000000000000101 ,
b00000000000000000000000000011100 F
b00000000000000000000000000000110 G
b00000000000000000000000000001000 H
b00000000000000001000000000000110 I
b00000000000000000000000000001000 J
b00000000000000000000000000100000 K
b1000 L
b00000000000000000000000000000101 M
b00000000000000000000000000000101 N
b00000000000000000000000000100100 O
b00000000000000000000000000000000 P
b00000000000000000000000000000101 Q
b00000000000000000000000000000101 R
1S
1T
b00000000000000000000000000011100 V
b00000000011000001000010001100011 W
b00000000000000000000000000000000 X
b1100011 Y
b01000 Z
b00001 [
b00110 \
b000 ]
b00000000000000000000000000001000 _
b00000000011000001000000000000000 `
1b
1d
1e
b00000000000000000000000000011100 f
b00000000000000000000000000001000 g
b00000000000000000000000000100100 h
b00000000000000000000000000100100 i
0j
0l
b00000000010100000000000010010011 m
b00000000000000000000000000000000 n
0o
#19
0T
#20
b00000000000000000000000000100100 F
b11111111111111111111111111110101 G
b11111111111111111111011111100000 H
b11111111111111111111111111110100 I
b11111111111111111111111111110100 J
b00000000000000000000000000101000 K
b0000 L
b00000000000000000000000000000000 M
b00000000000000000000000000000000 N
b00000000000000000000000000011000 O
b00000000000000000000000000000000 Q
b00000000000000000000000000000000 R
1T
b00000000000000000000000000100100 V
b11111111010111111111000001101111 W
b1101111 Y
b00000 Z
b11111 [
b10101 \
b111 ]
b1111111 ^
b11111111111111111111111111100000 _
b11111111010111111111000000000000 `
1a
0b
b00000000000000000000000000100100 f
b11111111111111111111111111110100 g
b00000000000000000000000000011000 h
b00000000000000000000000000011000 i
1l
b00000000000000000000000000101000 n
#21
0T
#22
b00000000000000000000000000011000 F
b00000000000000000000000000000100 G
b00000000000000000000000000000110 H
b00000000000000000010000000000100 I
b00000000000000000000000000000100 J
b00000000000000000000000000011100 K
b00000000000000000000000000011110 O
b00000000000000000000000000000100 P
b00000000000000000000000000000100 R
0S
1T
b00000000000000000000000000011000 V
b00000000010000000010001100000011 W
b00000000000000000000000000000100 X
b0000011 Y
b00110 Z
b00000 [
b00100 \
b010 ]
b0000000 ^
b00000000000000000000000000000110 _
b00000000010000000010000000000000 `
0a
0d
0e
b00000000000000000000000000011000 f
b00000000000000000000000000000110 g
b00000000000000000000000000011100 h
b00000000000000000000000000011110 i
1j
b00000000000000000000000000000101 m
b00000000000000000000000000000101 n
1o
